<gesmes:Envelope xmlns:gesmes="http://www.gesmes.org/xml/2002-08-01" xmlns="https://getexpenses.app/eurofxref">
<gesmes:subject>Reference rates</gesmes:subject>
<gesmes:Sender>
<gesmes:name>Expenses</gesmes:name>
</gesmes:Sender>
<Cube>
<Cube time="2023-10-25">
<Cube currency="AED" rate="3.889884"/>
<Cube currency="AFN" rate="78.899968"/>
<Cube currency="ALL" rate="105.97474"/>
<Cube currency="AMD" rate="426.168943"/>
<Cube currency="ANG" rate="1.908902"/>
<Cube currency="AOA" rate="876.33926"/>
<Cube currency="ARS" rate="370.696393"/>
<Cube currency="AUD" rate="1.672258"/>
<Cube currency="AWG" rate="1.906274"/>
<Cube currency="AZN" rate="1.80209"/>
<Cube currency="BAM" rate="1.959086"/>
<Cube currency="BBD" rate="2.138496"/>
<Cube currency="BDT" rate="116.770888"/>
<Cube currency="BGN" rate="1.955732"/>
<Cube currency="BHD" rate="0.399272"/>
<Cube currency="BIF" rate="3016.14945"/>
<Cube currency="BMD" rate="1.059041"/>
<Cube currency="BND" rate="1.45098"/>
<Cube currency="BOB" rate="7.319068"/>
<Cube currency="BRL" rate="5.290233"/>
<Cube currency="BSD" rate="1.058991"/>
<Cube currency="BTN" rate="88.082738"/>
<Cube currency="BWP" rate="14.586917"/>
<Cube currency="BYN" rate="3.489042"/>
<Cube currency="BYR" rate="20757.208294"/>
<Cube currency="BZD" rate="2.134707"/>
<Cube currency="CAD" rate="1.458619"/>
<Cube currency="CDF" rate="2737.621138"/>
<Cube currency="CHF" rate="0.947898"/>
<Cube currency="CLF" rate="0.035475"/>
<Cube currency="CLP" rate="978.501029"/>
<Cube currency="CNY" rate="7.749109"/>
<Cube currency="COP" rate="4453.744981"/>
<Cube currency="CRC" rate="562.944178"/>
<Cube currency="CUC" rate="1.059041"/>
<Cube currency="CUP" rate="28.064593"/>
<Cube currency="CVE" rate="110.450249"/>
<Cube currency="CZK" rate="24.705249"/>
<Cube currency="DJF" rate="188.553307"/>
<Cube currency="DKK" rate="7.464567"/>
<Cube currency="DOP" rate="60.200453"/>
<Cube currency="DZD" rate="144.86836"/>
<Cube currency="EGP" rate="32.721618"/>
<Cube currency="ERN" rate="15.885619"/>
<Cube currency="ETB" rate="59.149431"/>
<Cube currency="FJD" rate="2.421284"/>
<Cube currency="FKP" rate="0.870487"/>
<Cube currency="GBP" rate="0.87202"/>
<Cube currency="GEL" rate="2.854091"/>
<Cube currency="GHS" rate="12.52966"/>
<Cube currency="GIP" rate="0.870487"/>
<Cube currency="GMD" rate="69.896551"/>
<Cube currency="GNF" rate="9098.874142"/>
<Cube currency="GTQ" rate="8.303927"/>
<Cube currency="GYD" rate="221.595386"/>
<Cube currency="HKD" rate="8.284297"/>
<Cube currency="HNL" rate="26.149612"/>
<Cube currency="HRK" rate="7.592221"/>
<Cube currency="HTG" rate="141.382431"/>
<Cube currency="HUF" rate="385.290892"/>
<Cube currency="IDR" rate="16802.695354"/>
<Cube currency="ILS" rate="4.304388"/>
<Cube currency="INR" rate="88.040799"/>
<Cube currency="IQD" rate="1387.468127"/>
<Cube currency="IRR" rate="44757.662313"/>
<Cube currency="ISK" rate="147.559197"/>
<Cube currency="JMD" rate="163.916289"/>
<Cube currency="JOD" rate="0.751176"/>
<Cube currency="JPY" rate="158.790509"/>
<Cube currency="KES" rate="159.064525"/>
<Cube currency="KGS" rate="94.594111"/>
<Cube currency="KHR" rate="4383.586463"/>
<Cube currency="KMF" rate="492.559876"/>
<Cube currency="KPW" rate="953.140655"/>
<Cube currency="KRW" rate="1430.425841"/>
<Cube currency="KWD" rate="0.327424"/>
<Cube currency="KYD" rate="0.882526"/>
<Cube currency="KZT" rate="504.958715"/>
<Cube currency="LAK" rate="21932.163663"/>
<Cube currency="LBP" rate="15919.34921"/>
<Cube currency="LKR" rate="346.085754"/>
<Cube currency="LRD" rate="198.040651"/>
<Cube currency="LSL" rate="20.154022"/>
<Cube currency="LTL" rate="3.127073"/>
<Cube currency="LVL" rate="0.640603"/>
<Cube currency="LYD" rate="5.158652"/>
<Cube currency="MAD" rate="10.905085"/>
<Cube currency="MDL" rate="19.181628"/>
<Cube currency="MGA" rate="4801.917821"/>
<Cube currency="MKD" rate="61.645273"/>
<Cube currency="MMK" rate="2223.941535"/>
<Cube currency="MNT" rate="3664.768607"/>
<Cube currency="MOP" rate="8.533571"/>
<Cube currency="MRO" rate="378.07754"/>
<Cube currency="MUR" rate="47.016503"/>
<Cube currency="MVR" rate="16.319506"/>
<Cube currency="MWK" rate="1202.582924"/>
<Cube currency="MXN" rate="19.388376"/>
<Cube currency="MYR" rate="5.061904"/>
<Cube currency="MZN" rate="66.984305"/>
<Cube currency="NAD" rate="20.127092"/>
<Cube currency="NGN" rate="842.392996"/>
<Cube currency="NIO" rate="38.753351"/>
<Cube currency="NOK" rate="11.831069"/>
<Cube currency="NPR" rate="140.932382"/>
<Cube currency="NZD" rate="1.818829"/>
<Cube currency="OMR" rate="0.407662"/>
<Cube currency="PAB" rate="1.059176"/>
<Cube currency="PEN" rate="4.093349"/>
<Cube currency="PGK" rate="3.933911"/>
<Cube currency="PHP" rate="60.194886"/>
<Cube currency="PKR" rate="292.818067"/>
<Cube currency="PLN" rate="4.47268"/>
<Cube currency="PYG" rate="7861.812596"/>
<Cube currency="QAR" rate="3.855943"/>
<Cube currency="RON" rate="4.961815"/>
<Cube currency="RSD" rate="117.186107"/>
<Cube currency="RUB" rate="98.899652"/>
<Cube currency="RWF" rate="1306.763449"/>
<Cube currency="SAR" rate="3.972599"/>
<Cube currency="SBD" rate="8.904759"/>
<Cube currency="SCR" rate="13.597053"/>
<Cube currency="SDG" rate="635.986413"/>
<Cube currency="SEK" rate="11.756353"/>
<Cube currency="SGD" rate="1.450701"/>
<Cube currency="SHP" rate="1.288588"/>
<Cube currency="SLL" rate="20916.063927"/>
<Cube currency="SOS" rate="604.180356"/>
<Cube currency="SRD" rate="40.2425"/>
<Cube currency="STD" rate="21920.015462"/>
<Cube currency="SYP" rate="13769.360801"/>
<Cube currency="SZL" rate="20.283157"/>
<Cube currency="THB" rate="38.329891"/>
<Cube currency="TJS" rate="11.624367"/>
<Cube currency="TMT" rate="3.717235"/>
<Cube currency="TND" rate="3.343917"/>
<Cube currency="TOP" rate="2.545035"/>
<Cube currency="TRY" rate="29.778653"/>
<Cube currency="TTD" rate="7.201078"/>
<Cube currency="TWD" rate="34.29101"/>
<Cube currency="TZS" rate="2648.662495"/>
<Cube currency="UAH" rate="38.686427"/>
<Cube currency="UGX" rate="3985.515215"/>
<Cube currency="USD" rate="1.059041"/>
<Cube currency="UYU" rate="42.250464"/>
<Cube currency="UZS" rate="12916.541849"/>
<Cube currency="VND" rate="26025.938461"/>
<Cube currency="VUV" rate="129.981039"/>
<Cube currency="WST" rate="2.917965"/>
<Cube currency="XAF" rate="656.944077"/>
<Cube currency="XAG" rate="0.046645"/>
<Cube currency="XAU" rate="0.000537"/>
<Cube currency="XCD" rate="2.862112"/>
<Cube currency="XDR" rate="0.807513"/>
<Cube currency="XOF" rate="657.052814"/>
<Cube currency="XPF" rate="119.618347"/>
<Cube currency="YER" rate="265.131174"/>
<Cube currency="ZAR" rate="20.199306"/>
<Cube currency="ZMK" rate="9532.638661"/>
<Cube currency="ZMW" rate="23.116116"/>
<Cube currency="ZWL" rate="341.010847"/>
</Cube>
</Cube>
</gesmes:Envelope>