<gesmes:Envelope xmlns:gesmes="http://www.gesmes.org/xml/2002-08-01" xmlns="https://getexpenses.app/eurofxref">
<gesmes:subject>Reference rates</gesmes:subject>
<gesmes:Sender>
<gesmes:name>Expenses</gesmes:name>
</gesmes:Sender>
<Cube>
<Cube time="2023-02-05">
<Cube currency="AED" rate="3.977156"/>
<Cube currency="AFN" rate="98.003476"/>
<Cube currency="ALL" rate="116.172266"/>
<Cube currency="AMD" rate="432.981176"/>
<Cube currency="ANG" rate="1.969569"/>
<Cube currency="AOA" rate="546.161889"/>
<Cube currency="ARS" rate="202.94329"/>
<Cube currency="AUD" rate="1.564256"/>
<Cube currency="AWG" rate="1.951707"/>
<Cube currency="AZN" rate="1.845021"/>
<Cube currency="BAM" rate="1.9557"/>
<Cube currency="BBD" rate="2.206553"/>
<Cube currency="BDT" rate="117.31719"/>
<Cube currency="BGN" rate="1.95904"/>
<Cube currency="BHD" rate="0.406873"/>
<Cube currency="BIF" rate="2267.929023"/>
<Cube currency="BMD" rate="1.082778"/>
<Cube currency="BND" rate="1.432305"/>
<Cube currency="BOB" rate="7.551597"/>
<Cube currency="BRL" rate="5.57826"/>
<Cube currency="BSD" rate="1.092827"/>
<Cube currency="BTN" rate="89.426047"/>
<Cube currency="BWP" rate="13.921673"/>
<Cube currency="BYN" rate="2.759016"/>
<Cube currency="BYR" rate="21222.447211"/>
<Cube currency="BZD" rate="2.202853"/>
<Cube currency="CAD" rate="1.45206"/>
<Cube currency="CDF" rate="2214.281236"/>
<Cube currency="CHF" rate="1.0027"/>
<Cube currency="CLF" rate="0.031269"/>
<Cube currency="CLP" rate="856.300496"/>
<Cube currency="CNY" rate="7.33615"/>
<Cube currency="COP" rate="5012.866291"/>
<Cube currency="CRC" rate="612.42923"/>
<Cube currency="CUC" rate="1.082778"/>
<Cube currency="CUP" rate="28.693615"/>
<Cube currency="CVE" rate="110.25766"/>
<Cube currency="CZK" rate="23.843965"/>
<Cube currency="DJF" rate="194.557048"/>
<Cube currency="DKK" rate="7.465866"/>
<Cube currency="DOP" rate="61.88788"/>
<Cube currency="DZD" rate="146.73919"/>
<Cube currency="EGP" rate="32.668825"/>
<Cube currency="ERN" rate="16.241669"/>
<Cube currency="ETB" rate="58.668094"/>
<Cube currency="FJD" rate="2.354003"/>
<Cube currency="FKP" rate="0.898541"/>
<Cube currency="GBP" rate="0.898235"/>
<Cube currency="GEL" rate="2.848129"/>
<Cube currency="GHS" rate="13.387409"/>
<Cube currency="GIP" rate="0.898541"/>
<Cube currency="GMD" rate="66.049838"/>
<Cube currency="GNF" rate="9408.37368"/>
<Cube currency="GTQ" rate="8.578829"/>
<Cube currency="GYD" rate="230.594649"/>
<Cube currency="HKD" rate="8.497479"/>
<Cube currency="HNL" rate="26.942206"/>
<Cube currency="HRK" rate="7.625136"/>
<Cube currency="HTG" rate="163.89009"/>
<Cube currency="HUF" rate="389.432326"/>
<Cube currency="IDR" rate="16344.640964"/>
<Cube currency="ILS" rate="3.701098"/>
<Cube currency="INR" rate="89.040622"/>
<Cube currency="IQD" rate="1595.013819"/>
<Cube currency="IRR" rate="45693.228561"/>
<Cube currency="ISK" rate="153.975152"/>
<Cube currency="JMD" rate="168.84476"/>
<Cube currency="JOD" rate="0.768127"/>
<Cube currency="JPY" rate="142.039224"/>
<Cube currency="KES" rate="136.223432"/>
<Cube currency="KGS" rate="93.390012"/>
<Cube currency="KHR" rate="4491.600992"/>
<Cube currency="KMF" rate="488.661785"/>
<Cube currency="KPW" rate="974.500139"/>
<Cube currency="KRW" rate="1351.144841"/>
<Cube currency="KWD" rate="0.330302"/>
<Cube currency="KYD" rate="0.910739"/>
<Cube currency="KZT" rate="500.576676"/>
<Cube currency="LAK" rate="18404.674792"/>
<Cube currency="LBP" rate="16403.608004"/>
<Cube currency="LKR" rate="398.889346"/>
<Cube currency="LRD" rate="169.942408"/>
<Cube currency="LSL" rate="18.505088"/>
<Cube currency="LTL" rate="3.197162"/>
<Cube currency="LVL" rate="0.654962"/>
<Cube currency="LYD" rate="5.170556"/>
<Cube currency="MAD" rate="11.106261"/>
<Cube currency="MDL" rate="20.512734"/>
<Cube currency="MGA" rate="4667.2293"/>
<Cube currency="MKD" rate="61.610899"/>
<Cube currency="MMK" rate="2294.979422"/>
<Cube currency="MNT" rate="3788.996156"/>
<Cube currency="MOP" rate="8.831212"/>
<Cube currency="MRO" rate="386.551531"/>
<Cube currency="MUR" rate="49.006738"/>
<Cube currency="MVR" rate="16.621051"/>
<Cube currency="MWK" rate="1121.704328"/>
<Cube currency="MXN" rate="20.537703"/>
<Cube currency="MYR" rate="4.61051"/>
<Cube currency="MZN" rate="69.114123"/>
<Cube currency="NAD" rate="18.505083"/>
<Cube currency="NGN" rate="498.662951"/>
<Cube currency="NIO" rate="39.932342"/>
<Cube currency="NOK" rate="10.98828"/>
<Cube currency="NPR" rate="143.081475"/>
<Cube currency="NZD" rate="1.709875"/>
<Cube currency="OMR" rate="0.416827"/>
<Cube currency="PAB" rate="1.092827"/>
<Cube currency="PEN" rate="4.178022"/>
<Cube currency="PGK" rate="3.851544"/>
<Cube currency="PHP" rate="58.107319"/>
<Cube currency="PKR" rate="300.806175"/>
<Cube currency="PLN" rate="4.731244"/>
<Cube currency="PYG" rate="7986.56833"/>
<Cube currency="QAR" rate="3.942436"/>
<Cube currency="RON" rate="4.905746"/>
<Cube currency="RSD" rate="117.362187"/>
<Cube currency="RUB" rate="76.498664"/>
<Cube currency="RWF" rate="1183.141238"/>
<Cube currency="SAR" rate="4.062692"/>
<Cube currency="SBD" rate="8.875825"/>
<Cube currency="SCR" rate="14.41604"/>
<Cube currency="SDG" rate="632.887676"/>
<Cube currency="SEK" rate="11.421239"/>
<Cube currency="SGD" rate="1.432953"/>
<Cube currency="SHP" rate="1.491423"/>
<Cube currency="SLL" rate="21060.03089"/>
<Cube currency="SOS" rate="615.563215"/>
<Cube currency="SRD" rate="34.956444"/>
<Cube currency="STD" rate="22411.316802"/>
<Cube currency="SVC" rate="9.562363"/>
<Cube currency="SYP" rate="2719.710412"/>
<Cube currency="SZL" rate="18.739053"/>
<Cube currency="THB" rate="36.146416"/>
<Cube currency="TJS" rate="11.27275"/>
<Cube currency="TMT" rate="3.80055"/>
<Cube currency="TND" rate="3.29219"/>
<Cube currency="TOP" rate="2.503329"/>
<Cube currency="TRY" rate="20.381783"/>
<Cube currency="TTD" rate="7.417406"/>
<Cube currency="TWD" rate="32.462552"/>
<Cube currency="TZS" rate="2556.169834"/>
<Cube currency="UAH" rate="40.363413"/>
<Cube currency="UGX" rate="4026.031985"/>
<Cube currency="USD" rate="1.082778"/>
<Cube currency="UYU" rate="42.309183"/>
<Cube currency="UZS" rate="12367.816668"/>
<Cube currency="VND" rate="25391.142199"/>
<Cube currency="VUV" rate="124.012978"/>
<Cube currency="WST" rate="2.81826"/>
<Cube currency="XAF" rate="655.913336"/>
<Cube currency="XAG" rate="0.048456"/>
<Cube currency="XAU" rate="0.000581"/>
<Cube currency="XCD" rate="2.926262"/>
<Cube currency="XDR" rate="0.805146"/>
<Cube currency="XOF" rate="655.913336"/>
<Cube currency="XPF" rate="118.705337"/>
<Cube currency="YER" rate="271.131481"/>
<Cube currency="ZAR" rate="18.913716"/>
<Cube currency="ZMK" rate="9746.30449"/>
<Cube currency="ZMW" rate="20.87881"/>
<Cube currency="ZWL" rate="348.654048"/>
</Cube>
</Cube>
</gesmes:Envelope>