<gesmes:Envelope xmlns:gesmes="http://www.gesmes.org/xml/2002-08-01" xmlns="https://getexpenses.app/eurofxref">
<gesmes:subject>Reference rates</gesmes:subject>
<gesmes:Sender>
<gesmes:name>Expenses</gesmes:name>
</gesmes:Sender>
<Cube>
<Cube time="2023-05-14">
<Cube currency="AED" rate="4.017162"/>
<Cube currency="AFN" rate="95.941517"/>
<Cube currency="ALL" rate="110.951755"/>
<Cube currency="AMD" rate="423.106691"/>
<Cube currency="ANG" rate="1.965431"/>
<Cube currency="AOA" rate="557.923725"/>
<Cube currency="ARS" rate="249.712649"/>
<Cube currency="AUD" rate="1.645806"/>
<Cube currency="AWG" rate="1.969141"/>
<Cube currency="AZN" rate="1.864087"/>
<Cube currency="BAM" rate="1.955831"/>
<Cube currency="BBD" rate="2.201935"/>
<Cube currency="BDT" rate="117.111852"/>
<Cube currency="BGN" rate="1.971417"/>
<Cube currency="BHD" rate="0.409006"/>
<Cube currency="BIF" rate="3073.948611"/>
<Cube currency="BMD" rate="1.093967"/>
<Cube currency="BND" rate="1.454923"/>
<Cube currency="BOB" rate="7.536119"/>
<Cube currency="BRL" rate="5.382962"/>
<Cube currency="BSD" rate="1.090617"/>
<Cube currency="BTN" rate="89.632417"/>
<Cube currency="BWP" rate="14.737233"/>
<Cube currency="BYN" rate="2.752744"/>
<Cube currency="BYR" rate="21441.759079"/>
<Cube currency="BZD" rate="2.198235"/>
<Cube currency="CAD" rate="1.493868"/>
<Cube currency="CDF" rate="2499.715676"/>
<Cube currency="CHF" rate="0.982239"/>
<Cube currency="CLF" rate="0.031362"/>
<Cube currency="CLP" rate="865.363685"/>
<Cube currency="CNY" rate="7.612048"/>
<Cube currency="COP" rate="5013.879289"/>
<Cube currency="CRC" rate="583.609229"/>
<Cube currency="CUC" rate="1.093967"/>
<Cube currency="CUP" rate="28.990133"/>
<Cube currency="CVE" rate="110.271744"/>
<Cube currency="CZK" rate="23.794927"/>
<Cube currency="DJF" rate="194.173071"/>
<Cube currency="DKK" rate="7.507942"/>
<Cube currency="DOP" rate="59.530941"/>
<Cube currency="DZD" rate="147.718336"/>
<Cube currency="EGP" rate="33.52753"/>
<Cube currency="ERN" rate="16.409509"/>
<Cube currency="ETB" rate="59.503441"/>
<Cube currency="FJD" rate="2.430581"/>
<Cube currency="FKP" rate="0.878704"/>
<Cube currency="GBP" rate="0.878019"/>
<Cube currency="GEL" rate="2.81701"/>
<Cube currency="GHS" rate="12.705201"/>
<Cube currency="GIP" rate="0.878704"/>
<Cube currency="GMD" rate="65.474369"/>
<Cube currency="GNF" rate="9374.148242"/>
<Cube currency="GTQ" rate="8.506135"/>
<Cube currency="GYD" rate="230.653648"/>
<Cube currency="HKD" rate="8.585182"/>
<Cube currency="HNL" rate="26.800424"/>
<Cube currency="HRK" rate="7.596881"/>
<Cube currency="HTG" rate="158.682509"/>
<Cube currency="HUF" rate="373.584407"/>
<Cube currency="IDR" rate="16239.342886"/>
<Cube currency="ILS" rate="4.018963"/>
<Cube currency="INR" rate="89.924663"/>
<Cube currency="IQD" rate="1428.622592"/>
<Cube currency="IRR" rate="46220.118808"/>
<Cube currency="ISK" rate="151.766506"/>
<Cube currency="JMD" rate="168.742668"/>
<Cube currency="JOD" rate="0.776065"/>
<Cube currency="JPY" rate="148.489695"/>
<Cube currency="KES" rate="147.222328"/>
<Cube currency="KGS" rate="95.507504"/>
<Cube currency="KHR" rate="4490.071006"/>
<Cube currency="KMF" rate="496.059892"/>
<Cube currency="KPW" rate="984.57058"/>
<Cube currency="KRW" rate="1468.662459"/>
<Cube currency="KWD" rate="0.335794"/>
<Cube currency="KYD" rate="0.908914"/>
<Cube currency="KZT" rate="488.717729"/>
<Cube currency="LAK" rate="19111.302225"/>
<Cube currency="LBP" rate="16369.458866"/>
<Cube currency="LKR" rate="341.905407"/>
<Cube currency="LRD" rate="182.419465"/>
<Cube currency="LSL" rate="21.157745"/>
<Cube currency="LTL" rate="3.230201"/>
<Cube currency="LVL" rate="0.66173"/>
<Cube currency="LYD" rate="5.192082"/>
<Cube currency="MAD" rate="10.906672"/>
<Cube currency="MDL" rate="19.412307"/>
<Cube currency="MGA" rate="4793.075797"/>
<Cube currency="MKD" rate="61.620974"/>
<Cube currency="MMK" rate="2290.236218"/>
<Cube currency="MNT" rate="3792.530133"/>
<Cube currency="MOP" rate="8.809139"/>
<Cube currency="MRO" rate="390.546138"/>
<Cube currency="MUR" rate="49.611831"/>
<Cube currency="MVR" rate="16.803752"/>
<Cube currency="MWK" rate="1119.417702"/>
<Cube currency="MXN" rate="19.251313"/>
<Cube currency="MYR" rate="4.881833"/>
<Cube currency="MZN" rate="69.193845"/>
<Cube currency="NAD" rate="21.15774"/>
<Cube currency="NGN" rate="505.963953"/>
<Cube currency="NIO" rate="39.890631"/>
<Cube currency="NOK" rate="11.732537"/>
<Cube currency="NPR" rate="143.412268"/>
<Cube currency="NZD" rate="1.766886"/>
<Cube currency="OMR" rate="0.421156"/>
<Cube currency="PAB" rate="1.090517"/>
<Cube currency="PEN" rate="3.990963"/>
<Cube currency="PGK" rate="3.856061"/>
<Cube currency="PHP" rate="61.113431"/>
<Cube currency="PKR" rate="311.084319"/>
<Cube currency="PLN" rate="4.556872"/>
<Cube currency="PYG" rate="7877.124568"/>
<Cube currency="QAR" rate="3.983177"/>
<Cube currency="RON" rate="4.970664"/>
<Cube currency="RSD" rate="118.247334"/>
<Cube currency="RUB" rate="84.629719"/>
<Cube currency="RWF" rate="1219.619287"/>
<Cube currency="SAR" rate="4.102709"/>
<Cube currency="SBD" rate="9.117464"/>
<Cube currency="SCR" rate="15.122239"/>
<Cube currency="SDG" rate="656.380751"/>
<Cube currency="SEK" rate="11.457492"/>
<Cube currency="SGD" rate="1.464279"/>
<Cube currency="SHP" rate="1.331085"/>
<Cube currency="SLL" rate="21605.854544"/>
<Cube currency="SOS" rate="622.467764"/>
<Cube currency="SRD" rate="40.598772"/>
<Cube currency="STD" rate="22642.914398"/>
<Cube currency="SVC" rate="9.542151"/>
<Cube currency="SYP" rate="2748.080203"/>
<Cube currency="SZL" rate="20.958331"/>
<Cube currency="THB" rate="37.110694"/>
<Cube currency="TJS" rate="11.925389"/>
<Cube currency="TMT" rate="3.839825"/>
<Cube currency="TND" rate="3.331172"/>
<Cube currency="TOP" rate="2.569077"/>
<Cube currency="TRY" rate="21.418024"/>
<Cube currency="TTD" rate="7.402117"/>
<Cube currency="TWD" rate="33.72089"/>
<Cube currency="TZS" rate="2571.540666"/>
<Cube currency="UAH" rate="40.276337"/>
<Cube currency="UGX" rate="4059.06419"/>
<Cube currency="USD" rate="1.093967"/>
<Cube currency="UYU" rate="42.470672"/>
<Cube currency="UZS" rate="12503.197725"/>
<Cube currency="VND" rate="25664.472857"/>
<Cube currency="VUV" rate="128.729728"/>
<Cube currency="WST" rate="2.935236"/>
<Cube currency="XAF" rate="655.967373"/>
<Cube currency="XAG" rate="0.045652"/>
<Cube currency="XAU" rate="0.000544"/>
<Cube currency="XCD" rate="2.956502"/>
<Cube currency="XDR" rate="0.808313"/>
<Cube currency="XOF" rate="655.970373"/>
<Cube currency="XPF" rate="120.145"/>
<Cube currency="YER" rate="273.875111"/>
<Cube currency="ZAR" rate="21.272736"/>
<Cube currency="ZMK" rate="9847.022386"/>
<Cube currency="ZMW" rate="19.984316"/>
<Cube currency="ZWL" rate="352.257024"/>
</Cube>
</Cube>
</gesmes:Envelope>