<gesmes:Envelope xmlns:gesmes="http://www.gesmes.org/xml/2002-08-01" xmlns="https://getexpenses.app/eurofxref">
<gesmes:subject>Reference rates</gesmes:subject>
<gesmes:Sender>
<gesmes:name>Expenses</gesmes:name>
</gesmes:Sender>
<Cube>
<Cube time="2023-03-14">
<Cube currency="AED" rate="3.939579"/>
<Cube currency="AFN" rate="94.386978"/>
<Cube currency="ALL" rate="114.149877"/>
<Cube currency="AMD" rate="417.008634"/>
<Cube currency="ANG" rate="1.932096"/>
<Cube currency="AOA" rate="543.260857"/>
<Cube currency="ARS" rate="216.818966"/>
<Cube currency="AUD" rate="1.605348"/>
<Cube currency="AWG" rate="1.933328"/>
<Cube currency="AZN" rate="1.787104"/>
<Cube currency="BAM" rate="1.955657"/>
<Cube currency="BBD" rate="2.164741"/>
<Cube currency="BDT" rate="113.201707"/>
<Cube currency="BGN" rate="1.955748"/>
<Cube currency="BHD" rate="0.404261"/>
<Cube currency="BIF" rate="2232.041936"/>
<Cube currency="BMD" rate="1.072581"/>
<Cube currency="BND" rate="1.442148"/>
<Cube currency="BOB" rate="7.408561"/>
<Cube currency="BRL" rate="5.613358"/>
<Cube currency="BSD" rate="1.072096"/>
<Cube currency="BTN" rate="88.412047"/>
<Cube currency="BWP" rate="14.144359"/>
<Cube currency="BYN" rate="2.706152"/>
<Cube currency="BYR" rate="21022.595841"/>
<Cube currency="BZD" rate="2.161122"/>
<Cube currency="CAD" rate="1.465581"/>
<Cube currency="CDF" rate="2198.791666"/>
<Cube currency="CHF" rate="0.98139"/>
<Cube currency="CLF" rate="0.031165"/>
<Cube currency="CLP" rate="859.999049"/>
<Cube currency="CNY" rate="7.370736"/>
<Cube currency="COP" rate="5091.758519"/>
<Cube currency="CRC" rate="584.962598"/>
<Cube currency="CUC" rate="1.072581"/>
<Cube currency="CUP" rate="28.423408"/>
<Cube currency="CVE" rate="110.818706"/>
<Cube currency="CZK" rate="23.758058"/>
<Cube currency="DJF" rate="190.903133"/>
<Cube currency="DKK" rate="7.444176"/>
<Cube currency="DOP" rate="58.991965"/>
<Cube currency="DZD" rate="145.661403"/>
<Cube currency="EGP" rate="33.141161"/>
<Cube currency="ERN" rate="16.088721"/>
<Cube currency="ETB" rate="57.727377"/>
<Cube currency="FJD" rate="2.375662"/>
<Cube currency="FKP" rate="0.882358"/>
<Cube currency="GBP" rate="0.88194"/>
<Cube currency="GEL" rate="2.767099"/>
<Cube currency="GHS" rate="13.353301"/>
<Cube currency="GIP" rate="0.882358"/>
<Cube currency="GMD" rate="65.910048"/>
<Cube currency="GNF" rate="9438.716858"/>
<Cube currency="GTQ" rate="8.357388"/>
<Cube currency="GYD" rate="226.216591"/>
<Cube currency="HKD" rate="8.416906"/>
<Cube currency="HNL" rate="26.460517"/>
<Cube currency="HRK" rate="7.52767"/>
<Cube currency="HTG" rate="165.104056"/>
<Cube currency="HUF" rate="388.972315"/>
<Cube currency="IDR" rate="16490.778452"/>
<Cube currency="ILS" rate="3.87898"/>
<Cube currency="INR" rate="88.234822"/>
<Cube currency="IQD" rate="1567.041455"/>
<Cube currency="IRR" rate="45343.379293"/>
<Cube currency="ISK" rate="150.480361"/>
<Cube currency="JMD" rate="163.378031"/>
<Cube currency="JOD" rate="0.761643"/>
<Cube currency="JPY" rate="144.078251"/>
<Cube currency="KES" rate="138.906914"/>
<Cube currency="KGS" rate="93.764958"/>
<Cube currency="KHR" rate="4342.882373"/>
<Cube currency="KMF" rate="492.180846"/>
<Cube currency="KPW" rate="965.196434"/>
<Cube currency="KRW" rate="1399.445278"/>
<Cube currency="KWD" rate="0.329025"/>
<Cube currency="KYD" rate="0.893468"/>
<Cube currency="KZT" rate="494.55299"/>
<Cube currency="LAK" rate="18190.981184"/>
<Cube currency="LBP" rate="16356.866514"/>
<Cube currency="LKR" rate="364.534797"/>
<Cube currency="LRD" rate="172.417174"/>
<Cube currency="LSL" rate="19.531579"/>
<Cube currency="LTL" rate="3.167054"/>
<Cube currency="LVL" rate="0.648794"/>
<Cube currency="LYD" rate="5.158536"/>
<Cube currency="MAD" rate="11.179989"/>
<Cube currency="MDL" rate="20.000628"/>
<Cube currency="MGA" rate="4633.551659"/>
<Cube currency="MKD" rate="61.58006"/>
<Cube currency="MMK" rate="2251.466539"/>
<Cube currency="MNT" rate="3795.457714"/>
<Cube currency="MOP" rate="8.666007"/>
<Cube currency="MRO" rate="382.911383"/>
<Cube currency="MUR" rate="50.572334"/>
<Cube currency="MVR" rate="16.485014"/>
<Cube currency="MWK" rate="1126.210663"/>
<Cube currency="MXN" rate="19.985528"/>
<Cube currency="MYR" rate="4.82313"/>
<Cube currency="MZN" rate="67.680676"/>
<Cube currency="NAD" rate="19.532076"/>
<Cube currency="NGN" rate="493.956235"/>
<Cube currency="NIO" rate="39.213302"/>
<Cube currency="NOK" rate="11.278741"/>
<Cube currency="NPR" rate="141.45434"/>
<Cube currency="NZD" rate="1.720694"/>
<Cube currency="OMR" rate="0.412891"/>
<Cube currency="PAB" rate="1.072171"/>
<Cube currency="PEN" rate="4.057038"/>
<Cube currency="PGK" rate="3.776035"/>
<Cube currency="PHP" rate="58.799453"/>
<Cube currency="PKR" rate="302.414666"/>
<Cube currency="PLN" rate="4.687607"/>
<Cube currency="PYG" rate="7706.43541"/>
<Cube currency="QAR" rate="3.905809"/>
<Cube currency="RON" rate="4.922401"/>
<Cube currency="RSD" rate="117.307826"/>
<Cube currency="RUB" rate="80.953051"/>
<Cube currency="RWF" rate="1175.012946"/>
<Cube currency="SAR" rate="4.027514"/>
<Cube currency="SBD" rate="8.795344"/>
<Cube currency="SCR" rate="15.086317"/>
<Cube currency="SDG" rate="637.652666"/>
<Cube currency="SEK" rate="11.228448"/>
<Cube currency="SGD" rate="1.441968"/>
<Cube currency="SHP" rate="1.305063"/>
<Cube currency="SLL" rate="21183.482844"/>
<Cube currency="SOS" rate="609.763815"/>
<Cube currency="SRD" rate="36.432388"/>
<Cube currency="STD" rate="22200.26987"/>
<Cube currency="SVC" rate="9.381094"/>
<Cube currency="SYP" rate="2694.062281"/>
<Cube currency="SZL" rate="19.531714"/>
<Cube currency="THB" rate="37.098419"/>
<Cube currency="TJS" rate="11.707761"/>
<Cube currency="TMT" rate="3.764761"/>
<Cube currency="TND" rate="3.330367"/>
<Cube currency="TOP" rate="2.525983"/>
<Cube currency="TRY" rate="20.349441"/>
<Cube currency="TTD" rate="7.277535"/>
<Cube currency="TWD" rate="32.729288"/>
<Cube currency="TZS" rate="2508.809789"/>
<Cube currency="UAH" rate="39.402564"/>
<Cube currency="UGX" rate="4009.706241"/>
<Cube currency="USD" rate="1.072581"/>
<Cube currency="UYU" rate="42.105934"/>
<Cube currency="UZS" rate="12259.605117"/>
<Cube currency="VND" rate="25296.832801"/>
<Cube currency="VUV" rate="128.501046"/>
<Cube currency="WST" rate="2.954112"/>
<Cube currency="XAF" rate="655.97029"/>
<Cube currency="XAG" rate="0.048965"/>
<Cube currency="XAU" rate="0.000562"/>
<Cube currency="XCD" rate="2.898705"/>
<Cube currency="XDR" rate="0.807871"/>
<Cube currency="XOF" rate="655.884022"/>
<Cube currency="XPF" rate="119.56606"/>
<Cube currency="YER" rate="268.459268"/>
<Cube currency="ZAR" rate="19.432278"/>
<Cube currency="ZMK" rate="9654.51881"/>
<Cube currency="ZMW" rate="21.76971"/>
<Cube currency="ZWL" rate="345.37078"/>
</Cube>
</Cube>
</gesmes:Envelope>