<gesmes:Envelope xmlns:gesmes="http://www.gesmes.org/xml/2002-08-01" xmlns="https://getexpenses.app/eurofxref">
<gesmes:subject>Reference rates</gesmes:subject>
<gesmes:Sender>
<gesmes:name>Expenses</gesmes:name>
</gesmes:Sender>
<Cube>
<Cube time="2024-10-17">
<Cube currency="AED" rate="3.98056"/>
<Cube currency="AFN" rate="71.2959"/>
<Cube currency="ALL" rate="98.7"/>
<Cube currency="AMD" rate="419.354"/>
<Cube currency="ANG" rate="1.93991"/>
<Cube currency="AOA" rate="994.945"/>
<Cube currency="ARS" rate="1062.87"/>
<Cube currency="AUD" rate="1.61645"/>
<Cube currency="AWG" rate="1.93991"/>
<Cube currency="AZN" rate="1.84254"/>
<Cube currency="BAM" rate="1.95584"/>
<Cube currency="BBD" rate="2.1675"/>
<Cube currency="BDT" rate="129.508"/>
<Cube currency="BGN" rate="1.95606"/>
<Cube currency="BHD" rate="0.408628"/>
<Cube currency="BIF" rate="3139.35"/>
<Cube currency="BMD" rate="1.08375"/>
<Cube currency="BND" rate="1.42361"/>
<Cube currency="BOB" rate="7.46178"/>
<Cube currency="BRL" rate="6.14622"/>
<Cube currency="BSD" rate="1.08375"/>
<Cube currency="BTN" rate="91.0458"/>
<Cube currency="BWP" rate="14.4983"/>
<Cube currency="BYN" rate="3.54327"/>
<Cube currency="BYR" rate="21242.582708"/>
<Cube currency="BZD" rate="2.1675"/>
<Cube currency="CAD" rate="1.49379"/>
<Cube currency="CDF" rate="3078.38"/>
<Cube currency="CHF" rate="0.937175"/>
<Cube currency="CLF" rate="0.037155"/>
<Cube currency="CLP" rate="1024.69"/>
<Cube currency="CNY" rate="7.71896"/>
<Cube currency="COP" rate="4614.61"/>
<Cube currency="CRC" rate="557.915"/>
<Cube currency="CUC" rate="1.08375"/>
<Cube currency="CUP" rate="26.0189"/>
<Cube currency="CVE" rate="110.8"/>
<Cube currency="CZK" rate="25.242"/>
<Cube currency="DJF" rate="192.479"/>
<Cube currency="DKK" rate="7.4593"/>
<Cube currency="DOP" rate="65.1529"/>
<Cube currency="DZD" rate="144.494"/>
<Cube currency="EGP" rate="52.7031"/>
<Cube currency="ERN" rate="16.2563"/>
<Cube currency="ETB" rate="129.48"/>
<Cube currency="FJD" rate="2.42071"/>
<Cube currency="FKP" rate="0.833045"/>
<Cube currency="GBP" rate="0.833035"/>
<Cube currency="GEL" rate="2.94021"/>
<Cube currency="GHS" rate="17.2524"/>
<Cube currency="GIP" rate="0.833045"/>
<Cube currency="GMD" rate="75.402"/>
<Cube currency="GNF" rate="9349.53"/>
<Cube currency="GTQ" rate="8.37762"/>
<Cube currency="GYD" rate="226.558"/>
<Cube currency="HKD" rate="8.42524"/>
<Cube currency="HNL" rate="27.0291"/>
<Cube currency="HRK" rate="7.6086"/>
<Cube currency="HTG" rate="142.377"/>
<Cube currency="HUF" rate="400.225"/>
<Cube currency="IDR" rate="16792.7"/>
<Cube currency="ILS" rate="4.05994"/>
<Cube currency="INR" rate="91.0976"/>
<Cube currency="IQD" rate="1419.71"/>
<Cube currency="IRR" rate="45517.5"/>
<Cube currency="ISK" rate="149.102"/>
<Cube currency="JMD" rate="171.622"/>
<Cube currency="JOD" rate="0.767783"/>
<Cube currency="JPY" rate="162.555"/>
<Cube currency="KES" rate="139.804"/>
<Cube currency="KGS" rate="92.653"/>
<Cube currency="KHR" rate="4402.64"/>
<Cube currency="KMF" rate="491.968"/>
<Cube currency="KPW" rate="975.389"/>
<Cube currency="KRW" rate="1485.36"/>
<Cube currency="KWD" rate="0.332224"/>
<Cube currency="KYD" rate="0.888675"/>
<Cube currency="KZT" rate="527.385"/>
<Cube currency="LAK" rate="23763.5"/>
<Cube currency="LBP" rate="97025.2"/>
<Cube currency="LKR" rate="317.257"/>
<Cube currency="LRD" rate="208.587"/>
<Cube currency="LSL" rate="19.1803"/>
<Cube currency="LTL" rate="3.200195"/>
<Cube currency="LVL" rate="0.655582"/>
<Cube currency="LYD" rate="5.21186"/>
<Cube currency="MAD" rate="10.7345"/>
<Cube currency="MDL" rate="19.1472"/>
<Cube currency="MGA" rate="4970.51"/>
<Cube currency="MKD" rate="61.6118"/>
<Cube currency="MMK" rate="2277.02"/>
<Cube currency="MNT" rate="3673.0"/>
<Cube currency="MOP" rate="8.67797"/>
<Cube currency="MRU" rate="42.8813"/>
<Cube currency="MUR" rate="50.3341"/>
<Cube currency="MVR" rate="16.6776"/>
<Cube currency="MWK" rate="1879.23"/>
<Cube currency="MXN" rate="21.5088"/>
<Cube currency="MYR" rate="4.66988"/>
<Cube currency="MZN" rate="69.2043"/>
<Cube currency="NAD" rate="19.1803"/>
<Cube currency="NGN" rate="1816.03"/>
<Cube currency="NIO" rate="39.9156"/>
<Cube currency="NOK" rate="11.8449"/>
<Cube currency="NPR" rate="145.775"/>
<Cube currency="NZD" rate="1.78674"/>
<Cube currency="OMR" rate="0.417222"/>
<Cube currency="PAB" rate="1.08375"/>
<Cube currency="PEN" rate="4.07869"/>
<Cube currency="PGK" rate="4.23505"/>
<Cube currency="PHP" rate="62.6697"/>
<Cube currency="PKR" rate="301.228"/>
<Cube currency="PLN" rate="4.31775"/>
<Cube currency="PYG" rate="8555.56"/>
<Cube currency="QAR" rate="3.95059"/>
<Cube currency="RON" rate="4.97465"/>
<Cube currency="RSD" rate="117.003"/>
<Cube currency="RUB" rate="105.551"/>
<Cube currency="RWF" rate="1469.2"/>
<Cube currency="SAR" rate="4.07051"/>
<Cube currency="SBD" rate="8.86503"/>
<Cube currency="SCR" rate="14.7503"/>
<Cube currency="SDG" rate="651.725"/>
<Cube currency="SEK" rate="11.4038"/>
<Cube currency="SGD" rate="1.42356"/>
<Cube currency="SHP" rate="0.833045"/>
<Cube currency="SLE" rate="24.8066"/>
<Cube currency="SLL" rate="24806.6"/>
<Cube currency="SOS" rate="619.634"/>
<Cube currency="SRD" rate="35.3317"/>
<Cube currency="STD" rate="22432.580278"/>
<Cube currency="STN" rate="24.3287"/>
<Cube currency="SVC" rate="9.48281"/>
<Cube currency="SYP" rate="14118.4"/>
<Cube currency="SZL" rate="19.1804"/>
<Cube currency="THB" rate="35.9355"/>
<Cube currency="TJS" rate="11.5556"/>
<Cube currency="TMT" rate="3.79313"/>
<Cube currency="TND" rate="3.34857"/>
<Cube currency="TOP" rate="2.49367"/>
<Cube currency="TRY" rate="36.9839"/>
<Cube currency="TTD" rate="7.33688"/>
<Cube currency="TWD" rate="34.8534"/>
<Cube currency="TZS" rate="2952.57"/>
<Cube currency="UAH" rate="44.4338"/>
<Cube currency="UGX" rate="3979.9"/>
<Cube currency="USD" rate="1.08375"/>
<Cube currency="UYU" rate="45.4015"/>
<Cube currency="UZS" rate="13863.9"/>
<Cube currency="VEF" rate="10.824"/>
<Cube currency="VES" rate="41.1774"/>
<Cube currency="VND" rate="27232.1"/>
<Cube currency="VUV" rate="129.649"/>
<Cube currency="WST" rate="2.91683"/>
<Cube currency="XAF" rate="655.96"/>
<Cube currency="XAG" rate="0.034133"/>
<Cube currency="XAU" rate="0.000402"/>
<Cube currency="XCD" rate="2.92613"/>
<Cube currency="XDR" rate="0.809756"/>
<Cube currency="XOF" rate="655.957"/>
<Cube currency="XPF" rate="119.028"/>
<Cube currency="YER" rate="271.26"/>
<Cube currency="ZAR" rate="19.1803"/>
<Cube currency="ZMK" rate="9755.548161"/>
<Cube currency="ZMW" rate="28.8866"/>
<Cube currency="ZWL" rate="14.8813"/>
</Cube>
</Cube>
</gesmes:Envelope>