<gesmes:Envelope xmlns:gesmes="http://www.gesmes.org/xml/2002-08-01" xmlns="https://getexpenses.app/eurofxref">
<gesmes:subject>Reference rates</gesmes:subject>
<gesmes:Sender>
<gesmes:name>Expenses</gesmes:name>
</gesmes:Sender>
<Cube>
<Cube time="2024-11-04">
<Cube currency="AED" rate="4.00522"/>
<Cube currency="AFN" rate="73.687"/>
<Cube currency="ALL" rate="98.325"/>
<Cube currency="AMD" rate="422.091"/>
<Cube currency="ANG" rate="1.95191"/>
<Cube currency="AOA" rate="1001.19"/>
<Cube currency="ARS" rate="1081.94"/>
<Cube currency="AUD" rate="1.65045"/>
<Cube currency="AWG" rate="1.95191"/>
<Cube currency="AZN" rate="1.85338"/>
<Cube currency="BAM" rate="1.95578"/>
<Cube currency="BBD" rate="2.1809"/>
<Cube currency="BDT" rate="130.312"/>
<Cube currency="BGN" rate="1.95578"/>
<Cube currency="BHD" rate="0.411154"/>
<Cube currency="BIF" rate="3166.93"/>
<Cube currency="BMD" rate="1.09045"/>
<Cube currency="BND" rate="1.43563"/>
<Cube currency="BOB" rate="7.51402"/>
<Cube currency="BRL" rate="6.30395"/>
<Cube currency="BSD" rate="1.09045"/>
<Cube currency="BTN" rate="91.7372"/>
<Cube currency="BWP" rate="14.5103"/>
<Cube currency="BYN" rate="3.56646"/>
<Cube currency="BYR" rate="21373.230029"/>
<Cube currency="BZD" rate="2.1809"/>
<Cube currency="CAD" rate="1.51349"/>
<Cube currency="CDF" rate="3102.96"/>
<Cube currency="CHF" rate="0.94065"/>
<Cube currency="CLF" rate="0.037773"/>
<Cube currency="CLP" rate="1039.31"/>
<Cube currency="CNY" rate="7.74078"/>
<Cube currency="COP" rate="4825.22"/>
<Cube currency="CRC" rate="559.401"/>
<Cube currency="CUC" rate="1.09045"/>
<Cube currency="CUP" rate="26.1347"/>
<Cube currency="CVE" rate="110.646"/>
<Cube currency="CZK" rate="25.309"/>
<Cube currency="DJF" rate="194.005"/>
<Cube currency="DKK" rate="7.45835"/>
<Cube currency="DOP" rate="65.5524"/>
<Cube currency="DZD" rate="144.906"/>
<Cube currency="EGP" rate="53.5001"/>
<Cube currency="ERN" rate="16.3568"/>
<Cube currency="ETB" rate="132.781"/>
<Cube currency="FJD" rate="2.45045"/>
<Cube currency="FKP" rate="0.83968"/>
<Cube currency="GBP" rate="0.8397"/>
<Cube currency="GEL" rate="2.97693"/>
<Cube currency="GHS" rate="17.9413"/>
<Cube currency="GIP" rate="0.83968"/>
<Cube currency="GMD" rate="77.6479"/>
<Cube currency="GNF" rate="9400.91"/>
<Cube currency="GTQ" rate="8.4198"/>
<Cube currency="GYD" rate="228.231"/>
<Cube currency="HKD" rate="8.47612"/>
<Cube currency="HNL" rate="27.4597"/>
<Cube currency="HRK" rate="7.65564"/>
<Cube currency="HTG" rate="143.137"/>
<Cube currency="HUF" rate="407.385"/>
<Cube currency="IDR" rate="17177.3"/>
<Cube currency="ILS" rate="4.08232"/>
<Cube currency="INR" rate="91.7371"/>
<Cube currency="IQD" rate="1428.49"/>
<Cube currency="IRR" rate="45798.9"/>
<Cube currency="ISK" rate="148.895"/>
<Cube currency="JMD" rate="171.96"/>
<Cube currency="JOD" rate="0.773075"/>
<Cube currency="JPY" rate="165.67"/>
<Cube currency="KES" rate="140.614"/>
<Cube currency="KGS" rate="93.4859"/>
<Cube currency="KHR" rate="4427.33"/>
<Cube currency="KMF" rate="491.954"/>
<Cube currency="KPW" rate="981.402"/>
<Cube currency="KRW" rate="1498.22"/>
<Cube currency="KWD" rate="0.334163"/>
<Cube currency="KYD" rate="0.894169"/>
<Cube currency="KZT" rate="532.718"/>
<Cube currency="LAK" rate="23921.1"/>
<Cube currency="LBP" rate="97625.0"/>
<Cube currency="LKR" rate="319.584"/>
<Cube currency="LRD" rate="209.468"/>
<Cube currency="LSL" rate="19.0938"/>
<Cube currency="LTL" rate="3.219877"/>
<Cube currency="LVL" rate="0.659615"/>
<Cube currency="LYD" rate="5.24294"/>
<Cube currency="MAD" rate="10.7205"/>
<Cube currency="MDL" rate="19.4366"/>
<Cube currency="MGA" rate="5003.31"/>
<Cube currency="MKD" rate="61.5595"/>
<Cube currency="MMK" rate="2291.19"/>
<Cube currency="MNT" rate="3712.98"/>
<Cube currency="MOP" rate="8.73042"/>
<Cube currency="MRU" rate="43.1233"/>
<Cube currency="MUR" rate="49.9835"/>
<Cube currency="MVR" rate="16.7984"/>
<Cube currency="MWK" rate="1891.75"/>
<Cube currency="MXN" rate="21.7943"/>
<Cube currency="MYR" rate="4.76854"/>
<Cube currency="MZN" rate="69.5381"/>
<Cube currency="NAD" rate="19.0938"/>
<Cube currency="NGN" rate="1854.26"/>
<Cube currency="NIO" rate="40.1416"/>
<Cube currency="NOK" rate="11.9546"/>
<Cube currency="NPR" rate="146.757"/>
<Cube currency="NZD" rate="1.81908"/>
<Cube currency="OMR" rate="0.419851"/>
<Cube currency="PAB" rate="1.09045"/>
<Cube currency="PEN" rate="4.10282"/>
<Cube currency="PGK" rate="4.27544"/>
<Cube currency="PHP" rate="63.6753"/>
<Cube currency="PKR" rate="303.091"/>
<Cube currency="PLN" rate="4.34555"/>
<Cube currency="PYG" rate="8502.95"/>
<Cube currency="QAR" rate="3.97502"/>
<Cube currency="RON" rate="4.97535"/>
<Cube currency="RSD" rate="117.0"/>
<Cube currency="RUB" rate="108.111"/>
<Cube currency="RWF" rate="1484.77"/>
<Cube currency="SAR" rate="4.09622"/>
<Cube currency="SBD" rate="8.91619"/>
<Cube currency="SCR" rate="15.492"/>
<Cube currency="SDG" rate="655.653"/>
<Cube currency="SEK" rate="11.6351"/>
<Cube currency="SGD" rate="1.43563"/>
<Cube currency="SHP" rate="0.83968"/>
<Cube currency="SLE" rate="25.0524"/>
<Cube currency="SLL" rate="25052.4"/>
<Cube currency="SOS" rate="623.465"/>
<Cube currency="SRD" rate="37.1761"/>
<Cube currency="STD" rate="22570.546389"/>
<Cube currency="STN" rate="24.4719"/>
<Cube currency="SVC" rate="9.54144"/>
<Cube currency="SYP" rate="14202.8"/>
<Cube currency="SZL" rate="19.0938"/>
<Cube currency="THB" rate="36.71"/>
<Cube currency="TJS" rate="11.627"/>
<Cube currency="TMT" rate="3.81658"/>
<Cube currency="TND" rate="3.36426"/>
<Cube currency="TOP" rate="2.51227"/>
<Cube currency="TRY" rate="37.4544"/>
<Cube currency="TTD" rate="7.39194"/>
<Cube currency="TWD" rate="34.7908"/>
<Cube currency="TZS" rate="2932.84"/>
<Cube currency="UAH" rate="44.8175"/>
<Cube currency="UGX" rate="3988.78"/>
<Cube currency="USD" rate="1.09045"/>
<Cube currency="UYU" rate="45.3837"/>
<Cube currency="UZS" rate="13946.9"/>
<Cube currency="VEF" rate="10.8909"/>
<Cube currency="VES" rate="43.5257"/>
<Cube currency="VND" rate="27592.4"/>
<Cube currency="VUV" rate="131.803"/>
<Cube currency="WST" rate="2.94676"/>
<Cube currency="XAF" rate="655.941"/>
<Cube currency="XAG" rate="0.032327"/>
<Cube currency="XAU" rate="0.000401"/>
<Cube currency="XCD" rate="2.94422"/>
<Cube currency="XDR" rate="0.81968"/>
<Cube currency="XOF" rate="655.939"/>
<Cube currency="XPF" rate="119.183"/>
<Cube currency="YER" rate="272.726"/>
<Cube currency="ZAR" rate="19.0938"/>
<Cube currency="ZMK" rate="9815.545561"/>
<Cube currency="ZMW" rate="29.3098"/>
<Cube currency="ZWL" rate="14.9733"/>
</Cube>
</Cube>
</gesmes:Envelope>