<gesmes:Envelope xmlns:gesmes="http://www.gesmes.org/xml/2002-08-01" xmlns="https://getexpenses.app/eurofxref">
<gesmes:subject>Reference rates</gesmes:subject>
<gesmes:Sender>
<gesmes:name>Expenses</gesmes:name>
</gesmes:Sender>
<Cube>
<Cube time="2025-03-27">
<Cube currency="AED" rate="3.96587"/>
<Cube currency="AFN" rate="76.5162"/>
<Cube currency="ALL" rate="99.68"/>
<Cube currency="AMD" rate="423.008"/>
<Cube currency="ANG" rate="1.93275"/>
<Cube currency="AOA" rate="994.58"/>
<Cube currency="ARS" rate="1157.09"/>
<Cube currency="AUD" rate="1.71307"/>
<Cube currency="AWG" rate="1.93275"/>
<Cube currency="AZN" rate="1.8352"/>
<Cube currency="BAM" rate="1.95586"/>
<Cube currency="BBD" rate="2.1595"/>
<Cube currency="BDT" rate="131.19"/>
<Cube currency="BGN" rate="1.95591"/>
<Cube currency="BHD" rate="0.407023"/>
<Cube currency="BIF" rate="3195.58"/>
<Cube currency="BMD" rate="1.07975"/>
<Cube currency="BND" rate="1.44606"/>
<Cube currency="BOB" rate="7.4398"/>
<Cube currency="BRL" rate="6.19874"/>
<Cube currency="BSD" rate="1.07975"/>
<Cube currency="BTN" rate="92.51"/>
<Cube currency="BWP" rate="14.781"/>
<Cube currency="BYN" rate="3.53092"/>
<Cube currency="BYR" rate="21162.992836"/>
<Cube currency="BZD" rate="2.1595"/>
<Cube currency="CAD" rate="1.54485"/>
<Cube currency="CDF" rate="3095.1"/>
<Cube currency="CHF" rate="0.952105"/>
<Cube currency="CLF" rate="0.026146"/>
<Cube currency="CLP" rate="1011.89"/>
<Cube currency="CNY" rate="7.84563"/>
<Cube currency="COP" rate="4484.61"/>
<Cube currency="CRC" rate="539.799"/>
<Cube currency="CUC" rate="1.07975"/>
<Cube currency="CUP" rate="25.9356"/>
<Cube currency="CVE" rate="110.671"/>
<Cube currency="CZK" rate="24.973"/>
<Cube currency="DJF" rate="191.931"/>
<Cube currency="DKK" rate="7.4605"/>
<Cube currency="DOP" rate="68.1673"/>
<Cube currency="DZD" rate="144.296"/>
<Cube currency="EGP" rate="54.591"/>
<Cube currency="ERN" rate="16.1963"/>
<Cube currency="ETB" rate="141.176"/>
<Cube currency="FJD" rate="2.48104"/>
<Cube currency="FKP" rate="0.832659"/>
<Cube currency="GBP" rate="0.832645"/>
<Cube currency="GEL" rate="2.99064"/>
<Cube currency="GHS" rate="16.6488"/>
<Cube currency="GIP" rate="0.832659"/>
<Cube currency="GMD" rate="76.522"/>
<Cube currency="GNF" rate="9335.42"/>
<Cube currency="GTQ" rate="8.32754"/>
<Cube currency="GYD" rate="226.1"/>
<Cube currency="HKD" rate="8.39657"/>
<Cube currency="HNL" rate="27.6082"/>
<Cube currency="HRK" rate="7.58051"/>
<Cube currency="HTG" rate="141.547"/>
<Cube currency="HUF" rate="402.41"/>
<Cube currency="IDR" rate="17880.7"/>
<Cube currency="ILS" rate="3.96981"/>
<Cube currency="INR" rate="92.51"/>
<Cube currency="IQD" rate="1414.47"/>
<Cube currency="IRR" rate="45349.5"/>
<Cube currency="ISK" rate="142.9"/>
<Cube currency="JMD" rate="169.183"/>
<Cube currency="JOD" rate="0.765219"/>
<Cube currency="JPY" rate="162.885"/>
<Cube currency="KES" rate="139.666"/>
<Cube currency="KGS" rate="94.159"/>
<Cube currency="KHR" rate="4323.53"/>
<Cube currency="KMF" rate="491.975"/>
<Cube currency="KPW" rate="971.781"/>
<Cube currency="KRW" rate="1583.17"/>
<Cube currency="KWD" rate="0.332919"/>
<Cube currency="KYD" rate="0.885395"/>
<Cube currency="KZT" rate="540.118"/>
<Cube currency="LAK" rate="23373.2"/>
<Cube currency="LBP" rate="96704.9"/>
<Cube currency="LKR" rate="319.8"/>
<Cube currency="LRD" rate="214.768"/>
<Cube currency="LSL" rate="19.7226"/>
<Cube currency="LTL" rate="3.188205"/>
<Cube currency="LVL" rate="0.653127"/>
<Cube currency="LYD" rate="5.21681"/>
<Cube currency="MAD" rate="10.406"/>
<Cube currency="MDL" rate="19.4496"/>
<Cube currency="MGA" rate="5036.91"/>
<Cube currency="MKD" rate="61.628"/>
<Cube currency="MMK" rate="2270.71"/>
<Cube currency="MNT" rate="3763.04"/>
<Cube currency="MOP" rate="8.64847"/>
<Cube currency="MRU" rate="42.9598"/>
<Cube currency="MUR" rate="49.4497"/>
<Cube currency="MVR" rate="16.6259"/>
<Cube currency="MWK" rate="1871.54"/>
<Cube currency="MXN" rate="21.9374"/>
<Cube currency="MYR" rate="4.78545"/>
<Cube currency="MZN" rate="68.9251"/>
<Cube currency="NAD" rate="19.7222"/>
<Cube currency="NGN" rate="1646.51"/>
<Cube currency="NIO" rate="39.7346"/>
<Cube currency="NOK" rate="11.3464"/>
<Cube currency="NPR" rate="148.191"/>
<Cube currency="NZD" rate="1.87995"/>
<Cube currency="OMR" rate="0.415688"/>
<Cube currency="PAB" rate="1.07975"/>
<Cube currency="PEN" rate="3.94163"/>
<Cube currency="PGK" rate="4.38121"/>
<Cube currency="PHP" rate="61.9593"/>
<Cube currency="PKR" rate="302.438"/>
<Cube currency="PLN" rate="4.1904"/>
<Cube currency="PYG" rate="8619.86"/>
<Cube currency="QAR" rate="3.9358"/>
<Cube currency="RON" rate="4.978"/>
<Cube currency="RSD" rate="117.216"/>
<Cube currency="RUB" rate="91.1281"/>
<Cube currency="RWF" rate="1530.8"/>
<Cube currency="SAR" rate="4.0502"/>
<Cube currency="SBD" rate="8.87587"/>
<Cube currency="SCR" rate="15.6446"/>
<Cube currency="SDG" rate="648.399"/>
<Cube currency="SEK" rate="10.8295"/>
<Cube currency="SGD" rate="1.44606"/>
<Cube currency="SHP" rate="0.832659"/>
<Cube currency="SLE" rate="24.4997"/>
<Cube currency="SLL" rate="24494.0"/>
<Cube currency="SOS" rate="617.617"/>
<Cube currency="SRD" rate="39.3397"/>
<Cube currency="STD" rate="22348.531826"/>
<Cube currency="STN" rate="24.6207"/>
<Cube currency="SVC" rate="9.44781"/>
<Cube currency="SYP" rate="14038.7"/>
<Cube currency="SZL" rate="19.7222"/>
<Cube currency="THB" rate="36.5598"/>
<Cube currency="TJS" rate="11.7861"/>
<Cube currency="TMT" rate="3.77913"/>
<Cube currency="TND" rate="3.35424"/>
<Cube currency="TOP" rate="2.57728"/>
<Cube currency="TRY" rate="41.0405"/>
<Cube currency="TTD" rate="7.32027"/>
<Cube currency="TWD" rate="35.7548"/>
<Cube currency="TZS" rate="2865.18"/>
<Cube currency="UAH" rate="44.3777"/>
<Cube currency="UGX" rate="3957.35"/>
<Cube currency="USD" rate="1.07975"/>
<Cube currency="UYU" rate="45.5169"/>
<Cube currency="UZS" rate="13939.6"/>
<Cube currency="VEF" rate="10.784"/>
<Cube currency="VES" rate="72.4413"/>
<Cube currency="VND" rate="27621.9"/>
<Cube currency="VUV" rate="133.419"/>
<Cube currency="WST" rate="3.01396"/>
<Cube currency="XAF" rate="655.966"/>
<Cube currency="XAG" rate="0.031464"/>
<Cube currency="XAU" rate="0.000354"/>
<Cube currency="XCD" rate="2.91533"/>
<Cube currency="XDR" rate="0.818232"/>
<Cube currency="XOF" rate="655.966"/>
<Cube currency="XPF" rate="119.134"/>
<Cube currency="YER" rate="265.6"/>
<Cube currency="ZAR" rate="19.7222"/>
<Cube currency="ZMK" rate="9718.996851"/>
<Cube currency="ZMW" rate="31.0401"/>
<Cube currency="ZWL" rate="14.8264"/>
</Cube>
</Cube>
</gesmes:Envelope>