<gesmes:Envelope xmlns:gesmes="http://www.gesmes.org/xml/2002-08-01" xmlns="https://getexpenses.app/eurofxref">
<gesmes:subject>Reference rates</gesmes:subject>
<gesmes:Sender>
<gesmes:name>Expenses</gesmes:name>
</gesmes:Sender>
<Cube>
<Cube time="2024-01-08">
<Cube currency="AED" rate="4.027561"/>
<Cube currency="AFN" rate="77.156826"/>
<Cube currency="ALL" rate="104.612632"/>
<Cube currency="AMD" rate="443.301037"/>
<Cube currency="ANG" rate="1.975315"/>
<Cube currency="AOA" rate="910.675681"/>
<Cube currency="ARS" rate="892.562579"/>
<Cube currency="AUD" rate="1.635374"/>
<Cube currency="AWG" rate="1.973878"/>
<Cube currency="AZN" rate="1.860109"/>
<Cube currency="BAM" rate="1.959783"/>
<Cube currency="BBD" rate="2.212998"/>
<Cube currency="BDT" rate="120.284486"/>
<Cube currency="BGN" rate="1.957331"/>
<Cube currency="BHD" rate="0.413365"/>
<Cube currency="BIF" rate="3123.248198"/>
<Cube currency="BMD" rate="1.096599"/>
<Cube currency="BND" rate="1.459066"/>
<Cube currency="BOB" rate="7.573393"/>
<Cube currency="BRL" rate="5.356226"/>
<Cube currency="BSD" rate="1.096028"/>
<Cube currency="BTN" rate="91.129627"/>
<Cube currency="BWP" rate="14.851186"/>
<Cube currency="BYN" rate="3.619757"/>
<Cube currency="BYR" rate="21493.33856"/>
<Cube currency="BZD" rate="2.209291"/>
<Cube currency="CAD" rate="1.467028"/>
<Cube currency="CDF" rate="2949.850759"/>
<Cube currency="CHF" rate="0.929499"/>
<Cube currency="CLF" rate="0.035884"/>
<Cube currency="CLP" rate="990.404215"/>
<Cube currency="CNY" rate="7.787389"/>
<Cube currency="COP" rate="4277.920061"/>
<Cube currency="CRC" rate="569.557662"/>
<Cube currency="CUC" rate="1.096599"/>
<Cube currency="CUP" rate="29.059871"/>
<Cube currency="CVE" rate="110.488567"/>
<Cube currency="CZK" rate="24.480915"/>
<Cube currency="DJF" rate="195.146648"/>
<Cube currency="DKK" rate="7.459005"/>
<Cube currency="DOP" rate="64.070227"/>
<Cube currency="DZD" rate="147.141732"/>
<Cube currency="EGP" rate="33.886657"/>
<Cube currency="ERN" rate="16.448984"/>
<Cube currency="ETB" rate="61.953524"/>
<Cube currency="FJD" rate="2.424549"/>
<Cube currency="FKP" rate="0.862138"/>
<Cube currency="GBP" rate="0.86077"/>
<Cube currency="GEL" rate="2.950129"/>
<Cube currency="GHS" rate="13.130689"/>
<Cube currency="GIP" rate="0.862138"/>
<Cube currency="GMD" rate="73.684917"/>
<Cube currency="GNF" rate="9424.155187"/>
<Cube currency="GTQ" rate="8.573426"/>
<Cube currency="GYD" rate="229.306079"/>
<Cube currency="HKD" rate="8.562079"/>
<Cube currency="HNL" rate="27.046975"/>
<Cube currency="HRK" rate="7.656202"/>
<Cube currency="HTG" rate="144.42355"/>
<Cube currency="HUF" rate="377.350919"/>
<Cube currency="IDR" rate="17010.168082"/>
<Cube currency="ILS" rate="4.062684"/>
<Cube currency="INR" rate="91.091017"/>
<Cube currency="IQD" rate="1435.818391"/>
<Cube currency="IRR" rate="46098.278475"/>
<Cube currency="ISK" rate="150.716718"/>
<Cube currency="JMD" rate="169.233979"/>
<Cube currency="JOD" rate="0.777928"/>
<Cube currency="JPY" rate="158.006768"/>
<Cube currency="KES" rate="173.262598"/>
<Cube currency="KGS" rate="97.675708"/>
<Cube currency="KHR" rate="4489.124427"/>
<Cube currency="KMF" rate="493.442065"/>
<Cube currency="KPW" rate="986.939016"/>
<Cube currency="KRW" rate="1442.526541"/>
<Cube currency="KWD" rate="0.337138"/>
<Cube currency="KYD" rate="0.913356"/>
<Cube currency="KZT" rate="497.380958"/>
<Cube currency="LAK" rate="22595.927641"/>
<Cube currency="LBP" rate="16473.282982"/>
<Cube currency="LKR" rate="353.648813"/>
<Cube currency="LRD" rate="206.873507"/>
<Cube currency="LSL" rate="20.495097"/>
<Cube currency="LTL" rate="3.237972"/>
<Cube currency="LVL" rate="0.663322"/>
<Cube currency="LYD" rate="5.261695"/>
<Cube currency="MAD" rate="10.893642"/>
<Cube currency="MDL" rate="19.169964"/>
<Cube currency="MGA" rate="5013.189623"/>
<Cube currency="MKD" rate="61.550196"/>
<Cube currency="MMK" rate="2301.678306"/>
<Cube currency="MNT" rate="3741.640113"/>
<Cube currency="MOP" rate="8.813815"/>
<Cube currency="MUR" rate="49.290178"/>
<Cube currency="MVR" rate="16.884717"/>
<Cube currency="MWK" rate="1845.05018"/>
<Cube currency="MXN" rate="18.446882"/>
<Cube currency="MYR" rate="5.100241"/>
<Cube currency="MZN" rate="69.359826"/>
<Cube currency="NAD" rate="20.494956"/>
<Cube currency="NGN" rate="970.706035"/>
<Cube currency="NIO" rate="40.111529"/>
<Cube currency="NOK" rate="11.360502"/>
<Cube currency="NPR" rate="145.807363"/>
<Cube currency="NZD" rate="1.757552"/>
<Cube currency="OMR" rate="0.422123"/>
<Cube currency="PAB" rate="1.096028"/>
<Cube currency="PEN" rate="4.052938"/>
<Cube currency="PGK" rate="4.092318"/>
<Cube currency="PHP" rate="61.148002"/>
<Cube currency="PKR" rate="308.257853"/>
<Cube currency="PLN" rate="4.336751"/>
<Cube currency="PYG" rate="7951.161234"/>
<Cube currency="QAR" rate="3.992724"/>
<Cube currency="RON" rate="4.972858"/>
<Cube currency="RSD" rate="117.240715"/>
<Cube currency="RUB" rate="99.713889"/>
<Cube currency="RWF" rate="1389.92511"/>
<Cube currency="SAR" rate="4.11254"/>
<Cube currency="SBD" rate="9.254658"/>
<Cube currency="SCR" rate="14.77034"/>
<Cube currency="SDG" rate="659.056253"/>
<Cube currency="SEK" rate="11.206512"/>
<Cube currency="SGD" rate="1.457484"/>
<Cube currency="SHP" rate="1.394599"/>
<Cube currency="SLL" rate="21657.828871"/>
<Cube currency="SOS" rate="626.157718"/>
<Cube currency="SRD" rate="40.155234"/>
<Cube currency="STD" rate="22697.383332"/>
<Cube currency="SYP" rate="14257.820733"/>
<Cube currency="SZL" rate="20.543756"/>
<Cube currency="THB" rate="38.32573"/>
<Cube currency="TJS" rate="12.007005"/>
<Cube currency="TMT" rate="3.838096"/>
<Cube currency="TND" rate="3.396146"/>
<Cube currency="TOP" rate="2.571359"/>
<Cube currency="TRY" rate="32.783811"/>
<Cube currency="TTD" rate="7.43912"/>
<Cube currency="TWD" rate="33.955635"/>
<Cube currency="TZS" rate="2761.236387"/>
<Cube currency="UAH" rate="41.923212"/>
<Cube currency="UGX" rate="4175.486939"/>
<Cube currency="USD" rate="1.096599"/>
<Cube currency="UYU" rate="43.007415"/>
<Cube currency="UZS" rate="13541.523998"/>
<Cube currency="VND" rate="26696.700369"/>
<Cube currency="VUV" rate="129.376862"/>
<Cube currency="WST" rate="2.94152"/>
<Cube currency="XAF" rate="657.292989"/>
<Cube currency="XAG" rate="0.047445"/>
<Cube currency="XAU" rate="0.00054"/>
<Cube currency="XCD" rate="2.963613"/>
<Cube currency="XDR" rate="0.821269"/>
<Cube currency="XOF" rate="657.286983"/>
<Cube currency="XPF" rate="119.331742"/>
<Cube currency="YER" rate="274.589021"/>
<Cube currency="ZAR" rate="20.429311"/>
<Cube currency="ZMK" rate="9870.702809"/>
<Cube currency="ZMW" rate="28.447822"/>
<Cube currency="ZWL" rate="353.1044"/>
</Cube>
</Cube>
</gesmes:Envelope>