<gesmes:Envelope xmlns:gesmes="http://www.gesmes.org/xml/2002-08-01" xmlns="https://getexpenses.app/eurofxref">
<gesmes:subject>Reference rates</gesmes:subject>
<gesmes:Sender>
<gesmes:name>Expenses</gesmes:name>
</gesmes:Sender>
<Cube>
<Cube time="2024-07-23">
<Cube currency="AED" rate="3.98686"/>
<Cube currency="AFN" rate="76.6325"/>
<Cube currency="ALL" rate="100.365"/>
<Cube currency="AMD" rate="420.516"/>
<Cube currency="ANG" rate="1.94296"/>
<Cube currency="AOA" rate="961.555"/>
<Cube currency="ARS" rate="1005.38"/>
<Cube currency="AUD" rate="1.64015"/>
<Cube currency="AWG" rate="1.94296"/>
<Cube currency="AZN" rate="1.84407"/>
<Cube currency="BAM" rate="1.95582"/>
<Cube currency="BBD" rate="2.1709"/>
<Cube currency="BDT" rate="127.416"/>
<Cube currency="BGN" rate="1.95576"/>
<Cube currency="BHD" rate="0.409215"/>
<Cube currency="BIF" rate="3116.77"/>
<Cube currency="BMD" rate="1.08545"/>
<Cube currency="BND" rate="1.46053"/>
<Cube currency="BOB" rate="7.49883"/>
<Cube currency="BRL" rate="6.05269"/>
<Cube currency="BSD" rate="1.08545"/>
<Cube currency="BTN" rate="90.8467"/>
<Cube currency="BWP" rate="14.7881"/>
<Cube currency="BYN" rate="3.54951"/>
<Cube currency="BYR" rate="21274.044991"/>
<Cube currency="BZD" rate="2.1709"/>
<Cube currency="CAD" rate="1.49439"/>
<Cube currency="CDF" rate="3062.67"/>
<Cube currency="CHF" rate="0.967895"/>
<Cube currency="CLF" rate="0.037148"/>
<Cube currency="CLP" rate="1026.48"/>
<Cube currency="CNY" rate="7.89649"/>
<Cube currency="COP" rate="4353.79"/>
<Cube currency="CRC" rate="574.149"/>
<Cube currency="CUC" rate="1.08545"/>
<Cube currency="CUP" rate="26.0157"/>
<Cube currency="CVE" rate="110.582"/>
<Cube currency="CZK" rate="25.383"/>
<Cube currency="DJF" rate="192.947"/>
<Cube currency="DKK" rate="7.4609"/>
<Cube currency="DOP" rate="64.2858"/>
<Cube currency="DZD" rate="145.909"/>
<Cube currency="EGP" rate="52.4923"/>
<Cube currency="ERN" rate="16.2818"/>
<Cube currency="ETB" rate="62.6896"/>
<Cube currency="FJD" rate="2.45466"/>
<Cube currency="FKP" rate="0.840554"/>
<Cube currency="GBP" rate="0.84059"/>
<Cube currency="GEL" rate="2.95514"/>
<Cube currency="GHS" rate="16.043"/>
<Cube currency="GIP" rate="0.840554"/>
<Cube currency="GMD" rate="73.6858"/>
<Cube currency="GNF" rate="9348.2"/>
<Cube currency="GTQ" rate="8.41724"/>
<Cube currency="GYD" rate="226.208"/>
<Cube currency="HKD" rate="8.4753"/>
<Cube currency="HNL" rate="26.8811"/>
<Cube currency="HRK" rate="7.62053"/>
<Cube currency="HTG" rate="142.4"/>
<Cube currency="HUF" rate="389.835"/>
<Cube currency="IDR" rate="17595.1"/>
<Cube currency="ILS" rate="3.93318"/>
<Cube currency="INR" rate="90.8308"/>
<Cube currency="IQD" rate="1421.94"/>
<Cube currency="IRR" rate="45588.9"/>
<Cube currency="ISK" rate="149.694"/>
<Cube currency="JMD" rate="169.391"/>
<Cube currency="JOD" rate="0.769258"/>
<Cube currency="JPY" rate="169.365"/>
<Cube currency="KES" rate="143.811"/>
<Cube currency="KGS" rate="92.3718"/>
<Cube currency="KHR" rate="4461.2"/>
<Cube currency="KMF" rate="491.965"/>
<Cube currency="KPW" rate="976.908"/>
<Cube currency="KRW" rate="1504.41"/>
<Cube currency="KWD" rate="0.331909"/>
<Cube currency="KYD" rate="0.890069"/>
<Cube currency="KZT" rate="514.427"/>
<Cube currency="LAK" rate="24048.7"/>
<Cube currency="LBP" rate="97147.8"/>
<Cube currency="LKR" rate="329.412"/>
<Cube currency="LRD" rate="211.769"/>
<Cube currency="LSL" rate="19.9689"/>
<Cube currency="LTL" rate="3.204935"/>
<Cube currency="LVL" rate="0.656554"/>
<Cube currency="LYD" rate="5.25472"/>
<Cube currency="MAD" rate="10.7079"/>
<Cube currency="MDL" rate="19.2016"/>
<Cube currency="MGA" rate="4888.55"/>
<Cube currency="MKD" rate="61.4829"/>
<Cube currency="MMK" rate="2280.83"/>
<Cube currency="MNT" rate="3666.67"/>
<Cube currency="MOP" rate="8.72951"/>
<Cube currency="MRU" rate="42.9567"/>
<Cube currency="MUR" rate="50.5603"/>
<Cube currency="MVR" rate="16.5016"/>
<Cube currency="MWK" rate="1877.75"/>
<Cube currency="MXN" rate="19.6042"/>
<Cube currency="MYR" rate="5.07231"/>
<Cube currency="MZN" rate="69.2722"/>
<Cube currency="NAD" rate="19.9689"/>
<Cube currency="NGN" rate="1755.77"/>
<Cube currency="NIO" rate="39.9741"/>
<Cube currency="NOK" rate="11.978"/>
<Cube currency="NPR" rate="145.359"/>
<Cube currency="NZD" rate="1.82199"/>
<Cube currency="OMR" rate="0.417893"/>
<Cube currency="PAB" rate="1.08545"/>
<Cube currency="PEN" rate="4.07825"/>
<Cube currency="PGK" rate="4.19093"/>
<Cube currency="PHP" rate="63.4815"/>
<Cube currency="PKR" rate="302.059"/>
<Cube currency="PLN" rate="4.2762"/>
<Cube currency="PYG" rate="8214.25"/>
<Cube currency="QAR" rate="3.95809"/>
<Cube currency="RON" rate="4.97235"/>
<Cube currency="RSD" rate="117.048"/>
<Cube currency="RUB" rate="94.7055"/>
<Cube currency="RWF" rate="1423.59"/>
<Cube currency="SAR" rate="4.07174"/>
<Cube currency="SBD" rate="9.03037"/>
<Cube currency="SCR" rate="15.1574"/>
<Cube currency="SDG" rate="635.763"/>
<Cube currency="SEK" rate="11.6835"/>
<Cube currency="SGD" rate="1.46053"/>
<Cube currency="SHP" rate="0.840554"/>
<Cube currency="SLE" rate="24.5612"/>
<Cube currency="SLL" rate="24561.1"/>
<Cube currency="SOS" rate="620.335"/>
<Cube currency="SRD" rate="32.075"/>
<Cube currency="STD" rate="22465.80506"/>
<Cube currency="STN" rate="24.6588"/>
<Cube currency="SVC" rate="9.49769"/>
<Cube currency="SYP" rate="14113.0"/>
<Cube currency="SZL" rate="19.9689"/>
<Cube currency="THB" rate="39.2423"/>
<Cube currency="TJS" rate="11.5856"/>
<Cube currency="TMT" rate="3.79908"/>
<Cube currency="TND" rate="3.37032"/>
<Cube currency="TOP" rate="2.54085"/>
<Cube currency="TRY" rate="35.6403"/>
<Cube currency="TTD" rate="7.35859"/>
<Cube currency="TWD" rate="35.6418"/>
<Cube currency="TZS" rate="2914.62"/>
<Cube currency="UAH" rate="44.5577"/>
<Cube currency="UGX" rate="4013.39"/>
<Cube currency="USD" rate="1.08545"/>
<Cube currency="UYU" rate="43.6242"/>
<Cube currency="UZS" rate="13663.3"/>
<Cube currency="VEF" rate="10.8409"/>
<Cube currency="VES" rate="39.6833"/>
<Cube currency="VND" rate="27533.0"/>
<Cube currency="VUV" rate="130.884"/>
<Cube currency="WST" rate="2.96207"/>
<Cube currency="XAF" rate="655.954"/>
<Cube currency="XAG" rate="0.037359"/>
<Cube currency="XAU" rate="0.000451"/>
<Cube currency="XCD" rate="2.93072"/>
<Cube currency="XDR" rate="0.81825"/>
<Cube currency="XOF" rate="655.954"/>
<Cube currency="XPF" rate="119.141"/>
<Cube currency="YER" rate="271.637"/>
<Cube currency="ZAR" rate="19.9689"/>
<Cube currency="ZMK" rate="9769.994208"/>
<Cube currency="ZMW" rate="28.1946"/>
<Cube currency="ZWL" rate="14.9046"/>
</Cube>
</Cube>
</gesmes:Envelope>