<gesmes:Envelope xmlns:gesmes="http://www.gesmes.org/xml/2002-08-01" xmlns="https://getexpenses.app/eurofxref">
<gesmes:subject>Reference rates</gesmes:subject>
<gesmes:Sender>
<gesmes:name>Expenses</gesmes:name>
</gesmes:Sender>
<Cube>
<Cube time="2024-05-23">
<Cube currency="AED" rate="3.97571"/>
<Cube currency="AFN" rate="77.9185"/>
<Cube currency="ALL" rate="100.365"/>
<Cube currency="AMD" rate="419.352"/>
<Cube currency="ANG" rate="1.9375"/>
<Cube currency="AOA" rate="933.792"/>
<Cube currency="ARS" rate="963.612"/>
<Cube currency="AUD" rate="1.63418"/>
<Cube currency="AWG" rate="1.9375"/>
<Cube currency="AZN" rate="1.83911"/>
<Cube currency="BAM" rate="1.95584"/>
<Cube currency="BBD" rate="2.1648"/>
<Cube currency="BDT" rate="126.83"/>
<Cube currency="BGN" rate="1.95514"/>
<Cube currency="BHD" rate="0.408065"/>
<Cube currency="BIF" rate="3097.46"/>
<Cube currency="BMD" rate="1.0824"/>
<Cube currency="BND" rate="1.46259"/>
<Cube currency="BOB" rate="7.48772"/>
<Cube currency="BRL" rate="5.57658"/>
<Cube currency="BSD" rate="1.0824"/>
<Cube currency="BTN" rate="90.0773"/>
<Cube currency="BWP" rate="14.6866"/>
<Cube currency="BYN" rate="3.54038"/>
<Cube currency="BYR" rate="21215.574339"/>
<Cube currency="BZD" rate="2.1648"/>
<Cube currency="CAD" rate="1.48305"/>
<Cube currency="CDF" rate="3019.13"/>
<Cube currency="CHF" rate="0.989835"/>
<Cube currency="CLF" rate="0.035679"/>
<Cube currency="CLP" rate="984.962"/>
<Cube currency="CNY" rate="7.83939"/>
<Cube currency="COP" rate="4153.17"/>
<Cube currency="CRC" rate="557.106"/>
<Cube currency="CUC" rate="1.0824"/>
<Cube currency="CUP" rate="25.9552"/>
<Cube currency="CVE" rate="110.529"/>
<Cube currency="CZK" rate="24.73"/>
<Cube currency="DJF" rate="192.52"/>
<Cube currency="DKK" rate="7.46175"/>
<Cube currency="DOP" rate="63.7458"/>
<Cube currency="DZD" rate="145.396"/>
<Cube currency="EGP" rate="51.0348"/>
<Cube currency="ERN" rate="16.236"/>
<Cube currency="ETB" rate="62.0228"/>
<Cube currency="FJD" rate="2.45275"/>
<Cube currency="FKP" rate="0.851646"/>
<Cube currency="GBP" rate="0.85167"/>
<Cube currency="GEL" rate="2.94397"/>
<Cube currency="GHS" rate="15.0454"/>
<Cube currency="GIP" rate="0.851646"/>
<Cube currency="GMD" rate="73.0755"/>
<Cube currency="GNF" rate="9301.26"/>
<Cube currency="GTQ" rate="8.40598"/>
<Cube currency="GYD" rate="226.492"/>
<Cube currency="HKD" rate="8.45257"/>
<Cube currency="HNL" rate="26.778"/>
<Cube currency="HRK" rate="7.59912"/>
<Cube currency="HTG" rate="143.13"/>
<Cube currency="HUF" rate="386.885"/>
<Cube currency="IDR" rate="17310.3"/>
<Cube currency="ILS" rate="3.97793"/>
<Cube currency="INR" rate="90.1555"/>
<Cube currency="IQD" rate="1417.94"/>
<Cube currency="IRR" rate="45460.8"/>
<Cube currency="ISK" rate="150.102"/>
<Cube currency="JMD" rate="168.8"/>
<Cube currency="JOD" rate="0.767097"/>
<Cube currency="JPY" rate="170.05"/>
<Cube currency="KES" rate="143.959"/>
<Cube currency="KGS" rate="95.3167"/>
<Cube currency="KHR" rate="4415.11"/>
<Cube currency="KMF" rate="491.97"/>
<Cube currency="KPW" rate="974.173"/>
<Cube currency="KRW" rate="1478.99"/>
<Cube currency="KWD" rate="0.332318"/>
<Cube currency="KYD" rate="0.887568"/>
<Cube currency="KZT" rate="479.07"/>
<Cube currency="LAK" rate="23135.5"/>
<Cube currency="LBP" rate="96874.8"/>
<Cube currency="LKR" rate="324.628"/>
<Cube currency="LRD" rate="209.418"/>
<Cube currency="LSL" rate="19.9848"/>
<Cube currency="LTL" rate="3.196126"/>
<Cube currency="LVL" rate="0.65475"/>
<Cube currency="LYD" rate="5.23909"/>
<Cube currency="MAD" rate="10.7656"/>
<Cube currency="MDL" rate="19.0827"/>
<Cube currency="MGA" rate="4790.16"/>
<Cube currency="MKD" rate="61.4788"/>
<Cube currency="MMK" rate="2276.29"/>
<Cube currency="MNT" rate="3655.1"/>
<Cube currency="MOP" rate="8.70607"/>
<Cube currency="MRU" rate="42.661"/>
<Cube currency="MUR" rate="51.155"/>
<Cube currency="MVR" rate="16.4822"/>
<Cube currency="MWK" rate="1872.88"/>
<Cube currency="MXN" rate="18.1096"/>
<Cube currency="MYR" rate="5.09269"/>
<Cube currency="MZN" rate="68.8177"/>
<Cube currency="NAD" rate="19.9848"/>
<Cube currency="NGN" rate="1574.48"/>
<Cube currency="NIO" rate="39.8979"/>
<Cube currency="NOK" rate="11.5432"/>
<Cube currency="NPR" rate="144.228"/>
<Cube currency="NZD" rate="1.77167"/>
<Cube currency="OMR" rate="0.41661"/>
<Cube currency="PAB" rate="1.0824"/>
<Cube currency="PEN" rate="4.05332"/>
<Cube currency="PGK" rate="4.14554"/>
<Cube currency="PHP" rate="63.0159"/>
<Cube currency="PKR" rate="301.719"/>
<Cube currency="PLN" rate="4.26185"/>
<Cube currency="PYG" rate="8135.97"/>
<Cube currency="QAR" rate="3.94567"/>
<Cube currency="RON" rate="4.9746"/>
<Cube currency="RSD" rate="117.108"/>
<Cube currency="RUB" rate="98.0828"/>
<Cube currency="RWF" rate="1411.46"/>
<Cube currency="SAR" rate="4.05965"/>
<Cube currency="SBD" rate="8.97512"/>
<Cube currency="SCR" rate="15.1934"/>
<Cube currency="SDG" rate="649.903"/>
<Cube currency="SEK" rate="11.6227"/>
<Cube currency="SGD" rate="1.46259"/>
<Cube currency="SHP" rate="0.851646"/>
<Cube currency="SLE" rate="24.6267"/>
<Cube currency="SLL" rate="24626.7"/>
<Cube currency="SOS" rate="618.862"/>
<Cube currency="SRD" rate="35.0663"/>
<Cube currency="STD" rate="22404.058915"/>
<Cube currency="STN" rate="24.7508"/>
<Cube currency="SVC" rate="9.471"/>
<Cube currency="SYP" rate="14073.3"/>
<Cube currency="SZL" rate="19.9848"/>
<Cube currency="THB" rate="39.6472"/>
<Cube currency="TJS" rate="11.8077"/>
<Cube currency="TMT" rate="3.7884"/>
<Cube currency="TND" rate="3.37801"/>
<Cube currency="TOP" rate="2.51429"/>
<Cube currency="TRY" rate="34.8588"/>
<Cube currency="TTD" rate="7.32947"/>
<Cube currency="TWD" rate="34.889"/>
<Cube currency="TZS" rate="2810.57"/>
<Cube currency="UAH" rate="42.9713"/>
<Cube currency="UGX" rate="4139.32"/>
<Cube currency="USD" rate="1.0824"/>
<Cube currency="UYU" rate="41.5622"/>
<Cube currency="UZS" rate="13755.1"/>
<Cube currency="VEF" rate="10.8105"/>
<Cube currency="VES" rate="39.5957"/>
<Cube currency="VND" rate="27568.2"/>
<Cube currency="VUV" rate="130.462"/>
<Cube currency="WST" rate="2.93771"/>
<Cube currency="XAF" rate="655.96"/>
<Cube currency="XAG" rate="0.0358"/>
<Cube currency="XAU" rate="0.000462"/>
<Cube currency="XCD" rate="2.92248"/>
<Cube currency="XDR" rate="0.817742"/>
<Cube currency="XOF" rate="655.96"/>
<Cube currency="XPF" rate="119.435"/>
<Cube currency="YER" rate="270.915"/>
<Cube currency="ZAR" rate="19.9848"/>
<Cube currency="ZMK" rate="9743.146185"/>
<Cube currency="ZMW" rate="28.5447"/>
<Cube currency="ZWL" rate="14.8628"/>
</Cube>
</Cube>
</gesmes:Envelope>