<gesmes:Envelope xmlns:gesmes="http://www.gesmes.org/xml/2002-08-01" xmlns="https://getexpenses.app/eurofxref">
<gesmes:subject>Reference rates</gesmes:subject>
<gesmes:Sender>
<gesmes:name>Expenses</gesmes:name>
</gesmes:Sender>
<Cube>
<Cube time="2022-08-17">
<Cube currency="AED" rate="3.735999"/>
<Cube currency="AFN" rate="90.193398"/>
<Cube currency="ALL" rate="117.142335"/>
<Cube currency="AMD" rate="412.917827"/>
<Cube currency="ANG" rate="1.834538"/>
<Cube currency="AOA" rate="436.544491"/>
<Cube currency="ARS" rate="137.89573"/>
<Cube currency="AUD" rate="1.470407"/>
<Cube currency="AWG" rate="1.830851"/>
<Cube currency="AZN" rate="1.731139"/>
<Cube currency="BAM" rate="1.956618"/>
<Cube currency="BBD" rate="2.055227"/>
<Cube currency="BDT" rate="96.733045"/>
<Cube currency="BGN" rate="1.956285"/>
<Cube currency="BHD" rate="0.38343"/>
<Cube currency="BIF" rate="2098.624737"/>
<Cube currency="BMD" rate="1.017139"/>
<Cube currency="BND" rate="1.406566"/>
<Cube currency="BOB" rate="7.038733"/>
<Cube currency="BRL" rate="5.257387"/>
<Cube currency="BSD" rate="1.01791"/>
<Cube currency="BTN" rate="80.777468"/>
<Cube currency="BWP" rate="12.803754"/>
<Cube currency="BYN" rate="2.568234"/>
<Cube currency="BYR" rate="19935.932596"/>
<Cube currency="BZD" rate="2.051726"/>
<Cube currency="CAD" rate="1.314561"/>
<Cube currency="CDF" rate="2035.295784"/>
<Cube currency="CHF" rate="0.969766"/>
<Cube currency="CLF" rate="0.03302"/>
<Cube currency="CLP" rate="911.387159"/>
<Cube currency="CNY" rate="6.896922"/>
<Cube currency="COP" rate="4347.965871"/>
<Cube currency="CRC" rate="676.122152"/>
<Cube currency="CUC" rate="1.017139"/>
<Cube currency="CUP" rate="26.954195"/>
<Cube currency="CVE" rate="110.314284"/>
<Cube currency="CZK" rate="24.565035"/>
<Cube currency="DJF" rate="181.212942"/>
<Cube currency="DKK" rate="7.439055"/>
<Cube currency="DOP" rate="54.870086"/>
<Cube currency="DZD" rate="144.560973"/>
<Cube currency="EGP" rate="19.456145"/>
<Cube currency="ERN" rate="15.257091"/>
<Cube currency="ETB" rate="53.652296"/>
<Cube currency="FJD" rate="2.236995"/>
<Cube currency="FKP" rate="0.837721"/>
<Cube currency="GBP" rate="0.84449"/>
<Cube currency="GEL" rate="2.84692"/>
<Cube currency="GHS" rate="9.645009"/>
<Cube currency="GIP" rate="0.837721"/>
<Cube currency="GMD" rate="55.17978"/>
<Cube currency="GNF" rate="8787.325834"/>
<Cube currency="GTQ" rate="7.87497"/>
<Cube currency="GYD" rate="213.075767"/>
<Cube currency="HKD" rate="7.977373"/>
<Cube currency="HNL" rate="25.04208"/>
<Cube currency="HRK" rate="7.508318"/>
<Cube currency="HTG" rate="130.799649"/>
<Cube currency="HUF" rate="403.611139"/>
<Cube currency="IDR" rate="15026.658337"/>
<Cube currency="ILS" rate="3.306064"/>
<Cube currency="INR" rate="80.724812"/>
<Cube currency="IQD" rate="1485.734893"/>
<Cube currency="IRR" rate="43024.997535"/>
<Cube currency="ISK" rate="140.528007"/>
<Cube currency="JMD" rate="154.053009"/>
<Cube currency="JOD" rate="0.721182"/>
<Cube currency="JPY" rate="137.707451"/>
<Cube currency="KES" rate="121.639431"/>
<Cube currency="KGS" rate="82.369271"/>
<Cube currency="KHR" rate="4173.379866"/>
<Cube currency="KMF" rate="492.549882"/>
<Cube currency="KPW" rate="915.425833"/>
<Cube currency="KRW" rate="1339.018239"/>
<Cube currency="KWD" rate="0.312323"/>
<Cube currency="KYD" rate="0.848241"/>
<Cube currency="KZT" rate="485.60695"/>
<Cube currency="LAK" rate="15506.261166"/>
<Cube currency="LBP" rate="1539.219565"/>
<Cube currency="LKR" rate="366.4423"/>
<Cube currency="LRD" rate="156.181402"/>
<Cube currency="LSL" rate="16.660557"/>
<Cube currency="LTL" rate="3.003348"/>
<Cube currency="LVL" rate="0.615258"/>
<Cube currency="LYD" rate="4.965999"/>
<Cube currency="MAD" rate="10.613172"/>
<Cube currency="MDL" rate="19.579181"/>
<Cube currency="MGA" rate="4200.040597"/>
<Cube currency="MKD" rate="61.631628"/>
<Cube currency="MMK" rate="2137.579117"/>
<Cube currency="MNT" rate="3249.721345"/>
<Cube currency="MOP" rate="8.221956"/>
<Cube currency="MRO" rate="363.118597"/>
<Cube currency="MUR" rate="46.228833"/>
<Cube currency="MVR" rate="15.613028"/>
<Cube currency="MWK" rate="1044.772541"/>
<Cube currency="MXN" rate="20.383064"/>
<Cube currency="MYR" rate="4.544529"/>
<Cube currency="MZN" rate="64.924302"/>
<Cube currency="NAD" rate="16.660868"/>
<Cube currency="NGN" rate="427.666324"/>
<Cube currency="NIO" rate="36.582725"/>
<Cube currency="NOK" rate="9.888167"/>
<Cube currency="NPR" rate="129.234019"/>
<Cube currency="NZD" rate="1.622378"/>
<Cube currency="OMR" rate="0.391599"/>
<Cube currency="PAB" rate="1.01791"/>
<Cube currency="PEN" rate="3.908873"/>
<Cube currency="PGK" rate="3.587344"/>
<Cube currency="PHP" rate="56.834699"/>
<Cube currency="PKR" rate="218.592888"/>
<Cube currency="PLN" rate="4.705861"/>
<Cube currency="PYG" rate="6999.017239"/>
<Cube currency="QAR" rate="3.70342"/>
<Cube currency="RON" rate="4.879519"/>
<Cube currency="RSD" rate="117.357463"/>
<Cube currency="RUB" rate="61.589319"/>
<Cube currency="RWF" rate="1062.677748"/>
<Cube currency="SAR" rate="3.818562"/>
<Cube currency="SBD" rate="8.388894"/>
<Cube currency="SCR" rate="13.065956"/>
<Cube currency="SDG" rate="577.735365"/>
<Cube currency="SEK" rate="10.581179"/>
<Cube currency="SGD" rate="1.40764"/>
<Cube currency="SHP" rate="1.401005"/>
<Cube currency="SLL" rate="14173.837337"/>
<Cube currency="SOS" rate="575.70066"/>
<Cube currency="SRD" rate="24.588382"/>
<Cube currency="STD" rate="21052.73236"/>
<Cube currency="SVC" rate="8.906585"/>
<Cube currency="SYP" rate="2555.593679"/>
<Cube currency="SZL" rate="16.881295"/>
<Cube currency="THB" rate="36.106844"/>
<Cube currency="TJS" rate="10.40845"/>
<Cube currency="TMT" rate="3.570159"/>
<Cube currency="TND" rate="3.194869"/>
<Cube currency="TOP" rate="2.370242"/>
<Cube currency="TRY" rate="18.271907"/>
<Cube currency="TTD" rate="6.90558"/>
<Cube currency="TWD" rate="30.514633"/>
<Cube currency="TZS" rate="2373.735898"/>
<Cube currency="UAH" rate="37.587393"/>
<Cube currency="UGX" rate="3847.648753"/>
<Cube currency="USD" rate="1.017139"/>
<Cube currency="UYU" rate="40.822432"/>
<Cube currency="UZS" rate="11141.677666"/>
<Cube currency="VND" rate="23804.622373"/>
<Cube currency="VUV" rate="118.045213"/>
<Cube currency="WST" rate="2.713179"/>
<Cube currency="XAF" rate="656.221142"/>
<Cube currency="XAG" rate="0.051542"/>
<Cube currency="XAU" rate="0.000577"/>
<Cube currency="XCD" rate="2.74887"/>
<Cube currency="XDR" rate="0.77363"/>
<Cube currency="XOF" rate="656.250187"/>
<Cube currency="XPF" rate="119.617025"/>
<Cube currency="YER" rate="254.539707"/>
<Cube currency="ZAR" rate="16.965631"/>
<Cube currency="ZMK" rate="9155.472518"/>
<Cube currency="ZMW" rate="16.403403"/>
<Cube currency="ZWL" rate="327.518478"/>
</Cube>
</Cube>
</gesmes:Envelope>