<gesmes:Envelope xmlns:gesmes="http://www.gesmes.org/xml/2002-08-01" xmlns="https://getexpenses.app/eurofxref">
<gesmes:subject>Reference rates</gesmes:subject>
<gesmes:Sender>
<gesmes:name>Expenses</gesmes:name>
</gesmes:Sender>
<Cube>
<Cube time="2024-04-29">
<Cube currency="AED" rate="3.9379"/>
<Cube currency="AFN" rate="77.6884"/>
<Cube currency="ALL" rate="100.605"/>
<Cube currency="AMD" rate="416.622"/>
<Cube currency="ANG" rate="1.91915"/>
<Cube currency="AOA" rate="903.948"/>
<Cube currency="ARS" rate="939.92"/>
<Cube currency="AUD" rate="1.63238"/>
<Cube currency="AWG" rate="1.91915"/>
<Cube currency="AZN" rate="1.82308"/>
<Cube currency="BAM" rate="1.95576"/>
<Cube currency="BBD" rate="2.1443"/>
<Cube currency="BDT" rate="117.479"/>
<Cube currency="BGN" rate="1.95646"/>
<Cube currency="BHD" rate="0.404233"/>
<Cube currency="BIF" rate="3072.6"/>
<Cube currency="BMD" rate="1.07215"/>
<Cube currency="BND" rate="1.4577"/>
<Cube currency="BOB" rate="7.42464"/>
<Cube currency="BRL" rate="5.48828"/>
<Cube currency="BSD" rate="1.07215"/>
<Cube currency="BTN" rate="89.4613"/>
<Cube currency="BWP" rate="14.6971"/>
<Cube currency="BYN" rate="3.50607"/>
<Cube currency="BYR" rate="21014.59764"/>
<Cube currency="BZD" rate="2.1443"/>
<Cube currency="CAD" rate="1.4645"/>
<Cube currency="CDF" rate="2985.02"/>
<Cube currency="CHF" rate="0.976215"/>
<Cube currency="CLF" rate="0.036593"/>
<Cube currency="CLP" rate="1009.13"/>
<Cube currency="CNY" rate="7.75057"/>
<Cube currency="COP" rate="4139.98"/>
<Cube currency="CRC" rate="540.573"/>
<Cube currency="CUC" rate="1.07215"/>
<Cube currency="CUP" rate="25.7738"/>
<Cube currency="CVE" rate="110.719"/>
<Cube currency="CZK" rate="25.137"/>
<Cube currency="DJF" rate="190.567"/>
<Cube currency="DKK" rate="7.45795"/>
<Cube currency="DOP" rate="62.784"/>
<Cube currency="DZD" rate="143.904"/>
<Cube currency="EGP" rate="51.3025"/>
<Cube currency="ERN" rate="16.0823"/>
<Cube currency="ETB" rate="61.2936"/>
<Cube currency="FJD" rate="2.44003"/>
<Cube currency="FKP" rate="0.853453"/>
<Cube currency="GBP" rate="0.853435"/>
<Cube currency="GEL" rate="2.87872"/>
<Cube currency="GHS" rate="14.1417"/>
<Cube currency="GIP" rate="0.853453"/>
<Cube currency="GMD" rate="72.8593"/>
<Cube currency="GNF" rate="9215.39"/>
<Cube currency="GTQ" rate="8.33318"/>
<Cube currency="GYD" rate="224.347"/>
<Cube currency="HKD" rate="8.38984"/>
<Cube currency="HNL" rate="26.5651"/>
<Cube currency="HRK" rate="7.52716"/>
<Cube currency="HTG" rate="141.749"/>
<Cube currency="HUF" rate="391.19"/>
<Cube currency="IDR" rate="17427.8"/>
<Cube currency="ILS" rate="4.01627"/>
<Cube currency="INR" rate="89.4619"/>
<Cube currency="IQD" rate="1404.52"/>
<Cube currency="IRR" rate="45030.3"/>
<Cube currency="ISK" rate="150.294"/>
<Cube currency="JMD" rate="167.041"/>
<Cube currency="JOD" rate="0.760047"/>
<Cube currency="JPY" rate="167.5"/>
<Cube currency="KES" rate="144.542"/>
<Cube currency="KGS" rate="95.58"/>
<Cube currency="KHR" rate="4352.66"/>
<Cube currency="KMF" rate="491.962"/>
<Cube currency="KPW" rate="964.941"/>
<Cube currency="KRW" rate="1473.93"/>
<Cube currency="KWD" rate="0.330094"/>
<Cube currency="KYD" rate="0.879163"/>
<Cube currency="KZT" rate="473.536"/>
<Cube currency="LAK" rate="22890.1"/>
<Cube currency="LBP" rate="95986.7"/>
<Cube currency="LKR" rate="318.112"/>
<Cube currency="LRD" rate="207.157"/>
<Cube currency="LSL" rate="19.9804"/>
<Cube currency="LTL" rate="3.16585"/>
<Cube currency="LVL" rate="0.648547"/>
<Cube currency="LYD" rate="5.21376"/>
<Cube currency="MAD" rate="10.8336"/>
<Cube currency="MDL" rate="19.0242"/>
<Cube currency="MGA" rate="4756.71"/>
<Cube currency="MKD" rate="61.7277"/>
<Cube currency="MMK" rate="2254.73"/>
<Cube currency="MNT" rate="3619.58"/>
<Cube currency="MOP" rate="8.64153"/>
<Cube currency="MRU" rate="42.362"/>
<Cube currency="MUR" rate="50.8893"/>
<Cube currency="MVR" rate="16.5307"/>
<Cube currency="MWK" rate="1855.59"/>
<Cube currency="MXN" rate="18.2379"/>
<Cube currency="MYR" rate="5.10772"/>
<Cube currency="MZN" rate="68.3462"/>
<Cube currency="NAD" rate="19.9804"/>
<Cube currency="NGN" rate="1455.96"/>
<Cube currency="NIO" rate="39.4534"/>
<Cube currency="NOK" rate="11.7789"/>
<Cube currency="NPR" rate="143.196"/>
<Cube currency="NZD" rate="1.79274"/>
<Cube currency="OMR" rate="0.413292"/>
<Cube currency="PAB" rate="1.07215"/>
<Cube currency="PEN" rate="4.01016"/>
<Cube currency="PGK" rate="4.06579"/>
<Cube currency="PHP" rate="61.7897"/>
<Cube currency="PKR" rate="298.808"/>
<Cube currency="PLN" rate="4.3143"/>
<Cube currency="PYG" rate="8011.53"/>
<Cube currency="QAR" rate="3.90938"/>
<Cube currency="RON" rate="4.97595"/>
<Cube currency="RSD" rate="117.079"/>
<Cube currency="RUB" rate="100.042"/>
<Cube currency="RWF" rate="1386.29"/>
<Cube currency="SAR" rate="4.02121"/>
<Cube currency="SBD" rate="8.77014"/>
<Cube currency="SCR" rate="14.8289"/>
<Cube currency="SDG" rate="627.741"/>
<Cube currency="SEK" rate="11.7164"/>
<Cube currency="SGD" rate="1.4577"/>
<Cube currency="SHP" rate="0.853453"/>
<Cube currency="SLE" rate="24.273"/>
<Cube currency="SLL" rate="24273.0"/>
<Cube currency="SOS" rate="612.734"/>
<Cube currency="SRD" rate="36.5201"/>
<Cube currency="STD" rate="22191.823615"/>
<Cube currency="STN" rate="24.5714"/>
<Cube currency="SVC" rate="9.38131"/>
<Cube currency="SYP" rate="13939.8"/>
<Cube currency="SZL" rate="19.9804"/>
<Cube currency="THB" rate="39.6733"/>
<Cube currency="TJS" rate="11.7211"/>
<Cube currency="TMT" rate="3.75253"/>
<Cube currency="TND" rate="3.37068"/>
<Cube currency="TOP" rate="2.50766"/>
<Cube currency="TRY" rate="34.8805"/>
<Cube currency="TTD" rate="7.27931"/>
<Cube currency="TWD" rate="34.9231"/>
<Cube currency="TZS" rate="2774.86"/>
<Cube currency="UAH" rate="42.2963"/>
<Cube currency="UGX" rate="4091.49"/>
<Cube currency="USD" rate="1.07215"/>
<Cube currency="UYU" rate="41.0612"/>
<Cube currency="UZS" rate="13548.4"/>
<Cube currency="VEF" rate="10.7081"/>
<Cube currency="VES" rate="38.9525"/>
<Cube currency="VND" rate="27173.6"/>
<Cube currency="VUV" rate="130.781"/>
<Cube currency="WST" rate="2.93539"/>
<Cube currency="XAF" rate="655.949"/>
<Cube currency="XAG" rate="0.03947"/>
<Cube currency="XAU" rate="0.000459"/>
<Cube currency="XCD" rate="2.89481"/>
<Cube currency="XDR" rate="0.813569"/>
<Cube currency="XOF" rate="655.949"/>
<Cube currency="XPF" rate="119.265"/>
<Cube currency="YER" rate="268.343"/>
<Cube currency="ZAR" rate="19.9804"/>
<Cube currency="ZMK" rate="9650.843928"/>
<Cube currency="ZMW" rate="28.5627"/>
<Cube currency="ZWL" rate="14.722"/>
</Cube>
</Cube>
</gesmes:Envelope>