<gesmes:Envelope xmlns:gesmes="http://www.gesmes.org/xml/2002-08-01" xmlns="https://getexpenses.app/eurofxref">
<gesmes:subject>Reference rates</gesmes:subject>
<gesmes:Sender>
<gesmes:name>Expenses</gesmes:name>
</gesmes:Sender>
<Cube>
<Cube time="2022-11-16">
<Cube currency="AED" rate="3.813275"/>
<Cube currency="AFN" rate="91.942778"/>
<Cube currency="ALL" rate="116.427739"/>
<Cube currency="AMD" rate="410.557558"/>
<Cube currency="ANG" rate="1.870945"/>
<Cube currency="AOA" rate="521.087315"/>
<Cube currency="ARS" rate="168.657801"/>
<Cube currency="AUD" rate="1.538874"/>
<Cube currency="AWG" rate="1.871289"/>
<Cube currency="AZN" rate="1.766838"/>
<Cube currency="BAM" rate="1.949096"/>
<Cube currency="BBD" rate="2.095938"/>
<Cube currency="BDT" rate="106.769992"/>
<Cube currency="BGN" rate="1.955275"/>
<Cube currency="BHD" rate="0.391354"/>
<Cube currency="BIF" rate="2148.108229"/>
<Cube currency="BMD" rate="1.038163"/>
<Cube currency="BND" rate="1.420234"/>
<Cube currency="BOB" rate="7.173151"/>
<Cube currency="BRL" rate="5.539014"/>
<Cube currency="BSD" rate="1.038103"/>
<Cube currency="BTN" rate="84.359175"/>
<Cube currency="BWP" rate="13.412225"/>
<Cube currency="BYN" rate="2.621742"/>
<Cube currency="BYR" rate="20347.997129"/>
<Cube currency="BZD" rate="2.09245"/>
<Cube currency="CAD" rate="1.381546"/>
<Cube currency="CDF" rate="2125.119788"/>
<Cube currency="CHF" rate="0.97906"/>
<Cube currency="CLF" rate="0.034017"/>
<Cube currency="CLP" rate="939.429006"/>
<Cube currency="CNY" rate="7.35933"/>
<Cube currency="COP" rate="5087.206915"/>
<Cube currency="CRC" rate="635.817111"/>
<Cube currency="CUC" rate="1.038163"/>
<Cube currency="CUP" rate="27.511323"/>
<Cube currency="CVE" rate="109.883761"/>
<Cube currency="CZK" rate="24.348011"/>
<Cube currency="DJF" rate="184.801506"/>
<Cube currency="DKK" rate="7.437857"/>
<Cube currency="DOP" rate="56.544365"/>
<Cube currency="DZD" rate="143.919494"/>
<Cube currency="EGP" rate="25.448076"/>
<Cube currency="ERN" rate="15.572447"/>
<Cube currency="ETB" rate="55.439421"/>
<Cube currency="FJD" rate="2.30607"/>
<Cube currency="FKP" rate="0.873492"/>
<Cube currency="GBP" rate="0.876053"/>
<Cube currency="GEL" rate="2.823358"/>
<Cube currency="GHS" rate="15.05205"/>
<Cube currency="GIP" rate="0.873492"/>
<Cube currency="GMD" rate="63.844661"/>
<Cube currency="GNF" rate="8940.510299"/>
<Cube currency="GTQ" rate="8.102207"/>
<Cube currency="GYD" rate="217.177554"/>
<Cube currency="HKD" rate="8.123367"/>
<Cube currency="HNL" rate="25.65461"/>
<Cube currency="HRK" rate="7.544539"/>
<Cube currency="HTG" rate="141.797403"/>
<Cube currency="HUF" rate="410.111803"/>
<Cube currency="IDR" rate="16218.288059"/>
<Cube currency="ILS" rate="3.563651"/>
<Cube currency="INR" rate="84.559061"/>
<Cube currency="IQD" rate="1515.122509"/>
<Cube currency="IRR" rate="43966.208398"/>
<Cube currency="ISK" rate="148.859597"/>
<Cube currency="JMD" rate="159.668111"/>
<Cube currency="JOD" rate="0.736988"/>
<Cube currency="JPY" rate="144.755232"/>
<Cube currency="KES" rate="126.645395"/>
<Cube currency="KGS" rate="87.643499"/>
<Cube currency="KHR" rate="4301.857686"/>
<Cube currency="KMF" rate="495.724996"/>
<Cube currency="KPW" rate="934.397613"/>
<Cube currency="KRW" rate="1381.556244"/>
<Cube currency="KWD" rate="0.319723"/>
<Cube currency="KYD" rate="0.865016"/>
<Cube currency="KZT" rate="477.464251"/>
<Cube currency="LAK" rate="17951.011058"/>
<Cube currency="LBP" rate="1569.584603"/>
<Cube currency="LKR" rate="381.504977"/>
<Cube currency="LRD" rate="159.877087"/>
<Cube currency="LSL" rate="17.981313"/>
<Cube currency="LTL" rate="3.065426"/>
<Cube currency="LVL" rate="0.627974"/>
<Cube currency="LYD" rate="5.086278"/>
<Cube currency="MAD" rate="11.073341"/>
<Cube currency="MDL" rate="19.879316"/>
<Cube currency="MGA" rate="4485.519206"/>
<Cube currency="MKD" rate="61.402262"/>
<Cube currency="MMK" rate="2180.027743"/>
<Cube currency="MNT" rate="3546.176222"/>
<Cube currency="MOP" rate="8.364694"/>
<Cube currency="MRO" rate="370.624055"/>
<Cube currency="MUR" rate="45.364237"/>
<Cube currency="MVR" rate="15.988133"/>
<Cube currency="MWK" rate="1065.48446"/>
<Cube currency="MXN" rate="20.061567"/>
<Cube currency="MYR" rate="4.718415"/>
<Cube currency="MZN" rate="66.266192"/>
<Cube currency="NAD" rate="18.017341"/>
<Cube currency="NGN" rate="458.545998"/>
<Cube currency="NIO" rate="37.365541"/>
<Cube currency="NOK" rate="10.388286"/>
<Cube currency="NPR" rate="134.973912"/>
<Cube currency="NZD" rate="1.685157"/>
<Cube currency="OMR" rate="0.399693"/>
<Cube currency="PAB" rate="1.038004"/>
<Cube currency="PEN" rate="3.971241"/>
<Cube currency="PGK" rate="3.657868"/>
<Cube currency="PHP" rate="59.658058"/>
<Cube currency="PKR" rate="230.720721"/>
<Cube currency="PLN" rate="4.69774"/>
<Cube currency="PYG" rate="7365.018195"/>
<Cube currency="QAR" rate="3.779692"/>
<Cube currency="RON" rate="4.920059"/>
<Cube currency="RSD" rate="117.286489"/>
<Cube currency="RUB" rate="62.780317"/>
<Cube currency="RWF" rate="1107.633098"/>
<Cube currency="SAR" rate="3.902141"/>
<Cube currency="SBD" rate="8.544697"/>
<Cube currency="SCR" rate="13.290312"/>
<Cube currency="SDG" rate="590.197577"/>
<Cube currency="SEK" rate="10.877686"/>
<Cube currency="SGD" rate="1.42314"/>
<Cube currency="SHP" rate="1.429962"/>
<Cube currency="SLL" rate="18712.889927"/>
<Cube currency="SOS" rate="590.192572"/>
<Cube currency="SRD" rate="31.466883"/>
<Cube currency="STD" rate="21487.880517"/>
<Cube currency="SVC" rate="9.082532"/>
<Cube currency="SYP" rate="2608.430654"/>
<Cube currency="SZL" rate="17.886203"/>
<Cube currency="THB" rate="37.188047"/>
<Cube currency="TJS" rate="10.484323"/>
<Cube currency="TMT" rate="3.643953"/>
<Cube currency="TND" rate="3.343408"/>
<Cube currency="TOP" rate="2.45588"/>
<Cube currency="TRY" rate="19.321851"/>
<Cube currency="TTD" rate="7.049577"/>
<Cube currency="TWD" rate="32.317498"/>
<Cube currency="TZS" rate="2420.782493"/>
<Cube currency="UAH" rate="38.285224"/>
<Cube currency="UGX" rate="3892.812731"/>
<Cube currency="USD" rate="1.038163"/>
<Cube currency="UYU" rate="41.383219"/>
<Cube currency="UZS" rate="11610.603219"/>
<Cube currency="VND" rate="25730.8729"/>
<Cube currency="VUV" rate="124.190295"/>
<Cube currency="WST" rate="2.851118"/>
<Cube currency="XAF" rate="653.701592"/>
<Cube currency="XAG" rate="0.048342"/>
<Cube currency="XAU" rate="0.000585"/>
<Cube currency="XCD" rate="2.805688"/>
<Cube currency="XDR" rate="0.788797"/>
<Cube currency="XOF" rate="653.69218"/>
<Cube currency="XPF" rate="120.63315"/>
<Cube currency="YER" rate="259.696823"/>
<Cube currency="ZAR" rate="17.939771"/>
<Cube currency="ZMK" rate="9344.716081"/>
<Cube currency="ZMW" rate="17.189444"/>
<Cube currency="ZWL" rate="334.288101"/>
</Cube>
</Cube>
</gesmes:Envelope>