<gesmes:Envelope xmlns:gesmes="http://www.gesmes.org/xml/2002-08-01" xmlns="https://getexpenses.app/eurofxref">
<gesmes:subject>Reference rates</gesmes:subject>
<gesmes:Sender>
<gesmes:name>Expenses</gesmes:name>
</gesmes:Sender>
<Cube>
<Cube time="2023-05-02">
<Cube currency="AED" rate="4.034255"/>
<Cube currency="AFN" rate="95.575215"/>
<Cube currency="ALL" rate="111.22893"/>
<Cube currency="AMD" rate="424.979484"/>
<Cube currency="ANG" rate="1.97701"/>
<Cube currency="AOA" rate="557.474304"/>
<Cube currency="ARS" rate="246.822054"/>
<Cube currency="AUD" rate="1.647603"/>
<Cube currency="AWG" rate="1.977414"/>
<Cube currency="AZN" rate="1.853064"/>
<Cube currency="BAM" rate="1.958115"/>
<Cube currency="BBD" rate="2.214918"/>
<Cube currency="BDT" rate="116.407598"/>
<Cube currency="BGN" rate="1.959283"/>
<Cube currency="BHD" rate="0.414248"/>
<Cube currency="BIF" rate="2290.504976"/>
<Cube currency="BMD" rate="1.098564"/>
<Cube currency="BND" rate="1.465612"/>
<Cube currency="BOB" rate="7.596876"/>
<Cube currency="BRL" rate="5.543899"/>
<Cube currency="BSD" rate="1.096997"/>
<Cube currency="BTN" rate="89.813436"/>
<Cube currency="BWP" rate="14.528975"/>
<Cube currency="BYN" rate="2.768835"/>
<Cube currency="BYR" rate="21531.845334"/>
<Cube currency="BZD" rate="2.211183"/>
<Cube currency="CAD" rate="1.49715"/>
<Cube currency="CDF" rate="2300.39189"/>
<Cube currency="CHF" rate="0.981908"/>
<Cube currency="CLF" rate="0.032218"/>
<Cube currency="CLP" rate="888.979999"/>
<Cube currency="CNY" rate="7.593379"/>
<Cube currency="COP" rate="5181.605623"/>
<Cube currency="CRC" rate="593.092957"/>
<Cube currency="CUC" rate="1.098564"/>
<Cube currency="CUP" rate="29.111934"/>
<Cube currency="CVE" rate="110.570743"/>
<Cube currency="CZK" rate="23.604289"/>
<Cube currency="DJF" rate="195.318205"/>
<Cube currency="DKK" rate="7.45327"/>
<Cube currency="DOP" rate="59.816842"/>
<Cube currency="DZD" rate="149.191547"/>
<Cube currency="EGP" rate="33.943969"/>
<Cube currency="ERN" rate="16.478453"/>
<Cube currency="ETB" rate="59.487417"/>
<Cube currency="FJD" rate="2.436942"/>
<Cube currency="FKP" rate="0.879283"/>
<Cube currency="GBP" rate="0.881443"/>
<Cube currency="GEL" rate="2.729924"/>
<Cube currency="GHS" rate="12.954874"/>
<Cube currency="GIP" rate="0.879283"/>
<Cube currency="GMD" rate="65.968456"/>
<Cube currency="GNF" rate="9502.574516"/>
<Cube currency="GTQ" rate="8.562004"/>
<Cube currency="GYD" rate="232.011077"/>
<Cube currency="HKD" rate="8.623558"/>
<Cube currency="HNL" rate="27.057823"/>
<Cube currency="HRK" rate="7.487955"/>
<Cube currency="HTG" rate="170.027108"/>
<Cube currency="HUF" rate="374.344294"/>
<Cube currency="IDR" rate="16191.67305"/>
<Cube currency="ILS" rate="4.004868"/>
<Cube currency="INR" rate="89.786586"/>
<Cube currency="IQD" rate="1603.902765"/>
<Cube currency="IRR" rate="46414.309517"/>
<Cube currency="ISK" rate="150.09691"/>
<Cube currency="JMD" rate="167.936213"/>
<Cube currency="JOD" rate="0.779318"/>
<Cube currency="JPY" rate="150.024202"/>
<Cube currency="KES" rate="149.569563"/>
<Cube currency="KGS" rate="96.146284"/>
<Cube currency="KHR" rate="4537.067763"/>
<Cube currency="KMF" rate="492.320766"/>
<Cube currency="KPW" rate="988.704756"/>
<Cube currency="KRW" rate="1474.348795"/>
<Cube currency="KWD" rate="0.336765"/>
<Cube currency="KYD" rate="0.914168"/>
<Cube currency="KZT" rate="491.554321"/>
<Cube currency="LAK" rate="19142.469507"/>
<Cube currency="LBP" rate="16654.223152"/>
<Cube currency="LKR" rate="347.811124"/>
<Cube currency="LRD" rate="181.784817"/>
<Cube currency="LSL" rate="20.180679"/>
<Cube currency="LTL" rate="3.243772"/>
<Cube currency="LVL" rate="0.66451"/>
<Cube currency="LYD" rate="5.240619"/>
<Cube currency="MAD" rate="11.0488"/>
<Cube currency="MDL" rate="19.690005"/>
<Cube currency="MGA" rate="4850.157818"/>
<Cube currency="MKD" rate="61.692923"/>
<Cube currency="MMK" rate="2303.591466"/>
<Cube currency="MNT" rate="3837.266193"/>
<Cube currency="MOP" rate="8.869163"/>
<Cube currency="MRO" rate="392.186994"/>
<Cube currency="MUR" rate="49.3805"/>
<Cube currency="MVR" rate="16.862614"/>
<Cube currency="MWK" rate="1127.684669"/>
<Cube currency="MXN" rate="19.837058"/>
<Cube currency="MYR" rate="4.999582"/>
<Cube currency="MZN" rate="69.48423"/>
<Cube currency="NAD" rate="20.191475"/>
<Cube currency="NGN" rate="506.981126"/>
<Cube currency="NIO" rate="40.152553"/>
<Cube currency="NOK" rate="11.8818"/>
<Cube currency="NPR" rate="143.701898"/>
<Cube currency="NZD" rate="1.770802"/>
<Cube currency="OMR" rate="0.42298"/>
<Cube currency="PAB" rate="1.096982"/>
<Cube currency="PEN" rate="4.07182"/>
<Cube currency="PGK" rate="3.86673"/>
<Cube currency="PHP" rate="60.873052"/>
<Cube currency="PKR" rate="311.689929"/>
<Cube currency="PLN" rate="4.578572"/>
<Cube currency="PYG" rate="7924.258529"/>
<Cube currency="QAR" rate="3.999884"/>
<Cube currency="RON" rate="4.929582"/>
<Cube currency="RSD" rate="117.277185"/>
<Cube currency="RUB" rate="87.800277"/>
<Cube currency="RWF" rate="1225.447626"/>
<Cube currency="SAR" rate="4.119982"/>
<Cube currency="SBD" rate="9.118123"/>
<Cube currency="SCR" rate="15.347935"/>
<Cube currency="SDG" rate="658.589501"/>
<Cube currency="SEK" rate="11.334413"/>
<Cube currency="SGD" rate="1.467038"/>
<Cube currency="SHP" rate="1.336677"/>
<Cube currency="SLL" rate="21696.630093"/>
<Cube currency="SOS" rate="625.6289"/>
<Cube currency="SRD" rate="40.970938"/>
<Cube currency="STD" rate="22738.047234"/>
<Cube currency="SVC" rate="9.598346"/>
<Cube currency="SYP" rate="2760.173817"/>
<Cube currency="SZL" rate="20.191876"/>
<Cube currency="THB" rate="37.438778"/>
<Cube currency="TJS" rate="11.978796"/>
<Cube currency="TMT" rate="3.855958"/>
<Cube currency="TND" rate="3.345172"/>
<Cube currency="TOP" rate="2.597554"/>
<Cube currency="TRY" rate="21.383757"/>
<Cube currency="TTD" rate="7.435688"/>
<Cube currency="TWD" rate="33.846197"/>
<Cube currency="TZS" rate="2579.717232"/>
<Cube currency="UAH" rate="40.314803"/>
<Cube currency="UGX" rate="4102.8497"/>
<Cube currency="USD" rate="1.098564"/>
<Cube currency="UYU" rate="42.560308"/>
<Cube currency="UZS" rate="12551.089071"/>
<Cube currency="VND" rate="25777.793406"/>
<Cube currency="VUV" rate="131.145165"/>
<Cube currency="WST" rate="3.000422"/>
<Cube currency="XAF" rate="656.767353"/>
<Cube currency="XAG" rate="0.043514"/>
<Cube currency="XAU" rate="0.000546"/>
<Cube currency="XCD" rate="2.968923"/>
<Cube currency="XDR" rate="0.813951"/>
<Cube currency="XOF" rate="653.087104"/>
<Cube currency="XPF" rate="119.990569"/>
<Cube currency="YER" rate="274.966125"/>
<Cube currency="ZAR" rate="20.308419"/>
<Cube currency="ZMK" rate="9888.3941"/>
<Cube currency="ZMW" rate="19.498782"/>
<Cube currency="ZWL" rate="353.737011"/>
</Cube>
</Cube>
</gesmes:Envelope>